{"grid":["!!!!!!!!!!!!!!!!!!!!!!!!!!!!!!!!!!!!!!!!!!!!!!!!!!!!!!!!!!!!!!!#","!!!!!!!!!!!!!!!!!!!!!!!!!!!!!!!!!!!!!!!!!!!!!!!!!!!!!!!!!!!!!!!!","!!!!!!!!!!!!!!!!!!!!!!!!!!!!!!!!!!!!!!!!!!!!!!!!!!!!!!!!!!!!!!##","!!!!!!!!!!!!!!!!!!!!!!!!!!!!!!!!!!!!!!!!!!!!!!!!!!!!!!!!!!!!!###","!!!!!!!!!!!!!!!!!!!!!!!!!!!!!!!!!!!!!!!!!!!!!!!!!!!!!!!!!!#!!###","!!!!!!!!!!!!!!!!!!!!!!!!!!!!!!!!!!!!!!!!!!!!!!!!!!!!!!!!!#######","!!!!!!!!!!!!!!!!!!!!!!!!!!!!!!!!!!!!!!!!!!!!!!!!!!!!!!!!!#######","!!!!!!!!!!!!!!!!!!!!!!!!!!!!!!!!!!!!!!!!!!!!!!!!!!!!!!!!########","!!!!!!!!!!!!!!!!!!!!!!!!!!!!!!!!!!!!!!!!!!!!!!!!!!!!!!!#########","!!!!!!!!!!!!!!!!!!!!!!!!!!!!!!!!!!!!!!!!!!!!!!!!!!!!!!!#########","!!!!!!!!!!!!!!!!!!!!!!!!!!!!!!!!!!!!!!!!!!!!!!!!!!!!!!##########","!!!!!!!!!!!!!!!!!!!!!!!!!!!!!!!!!!!!!!!!!!!!!!!!!!!!!!##########","!!!!!!!!!!!!!!!!!!!!!!!!!!!!!!!!!!!!!!!!!!!!!!!!!!!!!!##########","!!!!!!!!!!!!!!!!!!!!!!!!!!!!!!!!!!!!!!!!!!!!!!!!!!!!!!##########","!!!!!!!!!!!!!!!!!!!!!!!!!!!!!!!!!!!!!!!!!!!!!!!!!!!!!!##########","!!!!!!!!!!!!!!!!!!!!!!!!!!!!!!!!!!!!!!!!!!!!!!!!!!!!!!##########","!!!!!!!!!!!!!!!!!!!!!!!!!!!!!!!!!!!!!!!!!!!!!!!!!!!!!###########","!!!!!!!!!!!!!!!!!!!!!!!!!!!!!!!!!!!!!!!!!!!!!!!!!!!!############","!!!!!!!!!!!!!!!!!!!!!!!!!!!!!!!!!!!!!!!!!!!!!!!!!!!!############","!!!!!!!!!!!!!!!!!!!!!!!!!!!!!!!!!!!!!!!!!!!!!!!!!!!#############","!!!!!!!!!!!!!!!!!!!!!!!!!!!!!!!!!!!!!!!!!!!!!!!!!!##############","!!!!!!!!!!!!!!!!!!!!!!!!!!!!!!!!!!!!!!!!!!!!!!!!!!##############","!!!!!!!!!!!!!!!!!!!!!!!!!!!!!!!!!!!!!!!!!!!!!!!!!!##############","!!!!!!!!!!!!!!!!!!!!!!!!!!!!!!!!!!!!!!!!!!!!!!!!!$$#############","!!!!!!!!!!!!!!!!!!!!!!!!!!!!!!!!!!!!!!!!!!!!!!!!$$$#############","%!!!!!!!!!!!!!!!!!!!!!!!!!!!!!!!!!!!!!!!!!!!!!$$$$$$############","%%!!!!!!!!!!!!!!!!!!!!!!!!!!!!!!!!!!!!!!!!!!!$$$$$$#############","%%!!!!!!!!!!!!!!!!!!!!!!!!!!!!!!!!!!!!!!!!!$$$$$$$$############&","'''!'!!!!!!!!!!!!!!!!!!!!!!!!!!!!!!!!!!!$$$$$$$$$$$#############","'''''!!!!!!!!!!!!!!!!!!!!!!!!!!!!!!!!!!$$$$$$$$$$$$############&","''''''!!!!!!!!!!!!!!!!!!!!!!!!!!!!!!!!!$$$$$$$$$$$$$###########&","''''''!!!!!!!!!!!!!!!!!!!!!!!!!!!!!!!!$$$$$$$$$$$$$##########&&&","'''''''!!!!!!!!!!!!!!!!!!!!!!!!!!!!!!!$$$$$$$$$$$$$##########&&&","''''''''!!!!!!!!!!!!!!!!!!!!!!!!!!!!!$$$$$$$$$$$$$$##########&&&","''''''''(!!!!!!!!!!!!!!!!!!!!!!!!!!!$$$$$$$$$$$$$$$##########&&&","'''''''(((!!!!!!!!!!!!!!!!!!!!!!!!!!$$$$$$$$$$$$$$$##########&&&","''''''(((((!!!!!!!!!!!!!!!!!!!!!!!!$$$$$$$$$$$$$$$##########&&&&","'''''(((((((((!!!!!!!!!!!!!!!!!!!!!$$$$$$$$$$$$$$$######&&&&&&&&","'''''((((((((((())!!!!!!!!!!!!!!!!!$$$$$$$$$$$$$$$$$$$##&&&&&&&&","'''''((((((((((()))!!!!!!!!!!!!!!!!$$$$$$$$$$$$$$$$$$$$$&&&&&&&&","'(((((((((((((()))))))!!!!!!!!!!!!$$$$$$$$$$$$$$$$$$$$$$&&&&&&&&","((((((((((((((()))))))))!!!!!!!!$$$$$$$$$$$$$$$$$$$$$$$$$&&&&&&&","((((((((((((()))))))))))))!!!!!$$$$$$$$$$$$$$$$$$$$$$$$$$&&&&&&&","((((((((((((()))))))))))))$$$$$$$$$$$$$$$$$$$$$$$$$$$$$$$$&&&&&&","((((((((((((())))))))))))$$$$$$$$$$$$$$$$$$$$$$$$$$$$$$$$$$&&&&&","(((((*(((((((()))))))))))$$$$$$$$$$$$$$$$$$$$$$$$$$$$$$$$$$&&&&&","(((****((((((()))))))))))$$$$$$$$$$$$$$$$$$$$$$$$$$$$$$$$$$&&&&&","(((*****((((((()))))))))))$$$$$$$$$$$$$$$$$$$$$$$$$$$$$$$$$$&&&&","(((******(((((((()))))))))$$$$$$$$$$$$$$$$$$$$$$$$$$$$$$$$$$&&&&","((********((((((())))))))$$$$$$$$$$$$$$$$$$$$$$$$$$$$$$$$$&&&&&&","(++********(((((()))))))$$$$$$$$$$$$$$$$$$$$$$$$$$$$$$$$$&&&&&&&","++****************))))))$$$$$$$$$$$$$$$$$$$$$$$$$$$$$$$$&&&&&&&&","+*******************)))$$$$$$$$$$$$$$$$$$$$$$$$$$$$$$$$&&&&&&&&&","+**********************$$$$$$$$$$$$$,,,,,$$$$$,,,$$$$$!&&&&&&&&&","+**********************$$$$$$$$$$$$,,,,,,$$$$$,,,,$$$,&&&&&&&&&&","+++*********************$$$$$$$$$$,,,,,,,,,$$$,,,,,,,,&&&&&&&&&&","++++********************$$$$$$$$$$,,,,,,,,,,,,,,,,,,,,,&&&&&&&&&","++++********************$$$$$$$$$$,,,,,,,,,,,,,,,,,,,,,,,&&&&&&&","-++*********************$$$$$$$$$$,,,,,,,,,,,,,,,,,,,,,,,,&&&&&&","--+*******************./$$$$$$$$$$,,,,,,,,,,,,,,,,,,,,,,,,&&&&&&","---******************../$$$$$$$$$$,,,,,,,,,,,,,,,,,,,,,,,&&&&&&&","---***************.....//$$,,$$$,,,,,,,,,,,,,,,,,,,,,,,,&&&&&&&&","----*...*****..........///,,,,,,,,,,,,,,,,,,,,,,,,,,,,,,,&&&&&&&","----................../////,,,,,,,,,,,,,,,,,,,,,,,,,,,,,,,&&&&&&"],"keys":["0",0,"4593","4610","4608","1339","4587","4622","4616","4653","4648","4582","1893","4604","4629"],"data":{"0":null,"1339":{"id":"540331","name":"Malá Morava","year":2010,"partyResults":[{"abbr":"Občané","percent":0,"count":0},{"abbr":"LIB","percent":0,"count":0},{"abbr":"VV","percent":0.08960573476702509,"count":25},{"abbr":"KONS","percent":0,"count":0},{"abbr":"ČSNS","percent":0,"count":0},{"abbr":"NP","percent":0,"count":0},{"abbr":"SPR-RSČ","percent":0,"count":0},{"abbr":"SPOZ","percent":0.017921146953405017,"count":5},{"abbr":"STOP","percent":0,"count":0},{"abbr":"TOP 09","percent":0.12903225806451613,"count":36},{"abbr":"ES","percent":0,"count":0},{"abbr":"Suveren","percent":0.03225806451612903,"count":9},{"abbr":"ČPS","percent":0.02867383512544803,"count":8},{"abbr":"DSSS","percent":0.0035842293906810036,"count":1},{"abbr":"Svobodní","percent":0.010752688172043012,"count":3},{"abbr":"KH","percent":null},{"abbr":"KČ","percent":0,"count":0},{"abbr":"PB","percent":0.014336917562724014,"count":4},{"abbr":"ČSNS2005","percent":0,"count":0},{"abbr":"M","percent":0,"count":0},{"abbr":"HS","percent":0,"count":0}]},"1893":{"id":"547964","name":"Sobkovice","year":2010,"partyResults":[{"abbr":"Občané","percent":0,"count":0},{"abbr":"LIB","percent":0,"count":0},{"abbr":"VV","percent":0.19834710743801653,"count":24},{"abbr":"KONS","percent":0,"count":0},{"abbr":"ČSNS","percent":0,"count":0},{"abbr":"NP","percent":0,"count":0},{"abbr":"SPR-RSČ","percent":0,"count":0},{"abbr":"SPOZ","percent":0.0743801652892562,"count":9},{"abbr":"STOP","percent":0,"count":0},{"abbr":"TOP 09","percent":0.09917355371900827,"count":12},{"abbr":"ES","percent":0,"count":0},{"abbr":"Suveren","percent":0.09090909090909091,"count":11},{"abbr":"ČPS","percent":0,"count":0},{"abbr":"DSSS","percent":0.008264462809917356,"count":1},{"abbr":"Svobodní","percent":0.024793388429752067,"count":3},{"abbr":"KH","percent":null},{"abbr":"KČ","percent":0,"count":0},{"abbr":"PB","percent":0,"count":0},{"abbr":"ČSNS2005","percent":0,"count":0},{"abbr":"M","percent":0,"count":0},{"abbr":"HS","percent":0,"count":0}]},"4582":{"id":"580015","name":"Cervená Voda","year":2010,"partyResults":[{"abbr":"Občané","percent":0.000715307582260372,"count":1},{"abbr":"LIB","percent":0,"count":0},{"abbr":"VV","percent":0.10014306151645208,"count":140},{"abbr":"KONS","percent":0.002145922746781116,"count":3},{"abbr":"ČSNS","percent":0,"count":0},{"abbr":"NP","percent":0,"count":0},{"abbr":"SPR-RSČ","percent":0,"count":0},{"abbr":"SPOZ","percent":0.033619456366237484,"count":47},{"abbr":"STOP","percent":0.000715307582260372,"count":1},{"abbr":"TOP 09","percent":0.11516452074391989,"count":161},{"abbr":"ES","percent":0,"count":0},{"abbr":"Suveren","percent":0.024320457796852647,"count":34},{"abbr":"ČPS","percent":0.007868383404864092,"count":11},{"abbr":"DSSS","percent":0.012875536480686695,"count":18},{"abbr":"Svobodní","percent":0.010014306151645207,"count":14},{"abbr":"KH","percent":null},{"abbr":"KČ","percent":0,"count":0},{"abbr":"PB","percent":0.009298998569384835,"count":13},{"abbr":"ČSNS2005","percent":0,"count":0},{"abbr":"M","percent":0,"count":0},{"abbr":"HS","percent":0,"count":0}]},"4587":{"id":"580066","name":"Ceské Petrovice","year":2010,"partyResults":[{"abbr":"Občané","percent":0,"count":0},{"abbr":"LIB","percent":0,"count":0},{"abbr":"VV","percent":0.05813953488372093,"count":5},{"abbr":"KONS","percent":0,"count":0},{"abbr":"ČSNS","percent":0,"count":0},{"abbr":"NP","percent":0,"count":0},{"abbr":"SPR-RSČ","percent":0,"count":0},{"abbr":"SPOZ","percent":0.011627906976744186,"count":1},{"abbr":"STOP","percent":0,"count":0},{"abbr":"TOP 09","percent":0.12790697674418605,"count":11},{"abbr":"ES","percent":0,"count":0},{"abbr":"Suveren","percent":0.05813953488372093,"count":5},{"abbr":"ČPS","percent":0,"count":0},{"abbr":"DSSS","percent":0,"count":0},{"abbr":"Svobodní","percent":0,"count":0},{"abbr":"KH","percent":null},{"abbr":"KČ","percent":0,"count":0},{"abbr":"PB","percent":0.023255813953488372,"count":2},{"abbr":"ČSNS2005","percent":0,"count":0},{"abbr":"M","percent":0,"count":0},{"abbr":"HS","percent":0,"count":0}]},"4593":{"id":"580163","name":"Dolní Morava","year":2010,"partyResults":[{"abbr":"Občané","percent":0,"count":0},{"abbr":"LIB","percent":0,"count":0},{"abbr":"VV","percent":0.06153846153846154,"count":8},{"abbr":"KONS","percent":0,"count":0},{"abbr":"ČSNS","percent":0,"count":0},{"abbr":"NP","percent":0,"count":0},{"abbr":"SPR-RSČ","percent":0,"count":0},{"abbr":"SPOZ","percent":0.007692307692307693,"count":1},{"abbr":"STOP","percent":0,"count":0},{"abbr":"TOP 09","percent":0.13076923076923078,"count":17},{"abbr":"ES","percent":0,"count":0},{"abbr":"Suveren","percent":0.03076923076923077,"count":4},{"abbr":"ČPS","percent":0.007692307692307693,"count":1},{"abbr":"DSSS","percent":0.015384615384615385,"count":2},{"abbr":"Svobodní","percent":0.023076923076923078,"count":3},{"abbr":"KH","percent":null},{"abbr":"KČ","percent":0,"count":0},{"abbr":"PB","percent":0.015384615384615385,"count":2},{"abbr":"ČSNS2005","percent":0,"count":0},{"abbr":"M","percent":0,"count":0},{"abbr":"HS","percent":0,"count":0}]},"4604":{"id":"580392","name":"Jamné nad Orlicí","year":2010,"partyResults":[{"abbr":"Občané","percent":0,"count":0},{"abbr":"LIB","percent":0,"count":0},{"abbr":"VV","percent":0.09511568123393316,"count":37},{"abbr":"KONS","percent":0,"count":0},{"abbr":"ČSNS","percent":0,"count":0},{"abbr":"NP","percent":0,"count":0},{"abbr":"SPR-RSČ","percent":0,"count":0},{"abbr":"SPOZ","percent":0.02570694087403599,"count":10},{"abbr":"STOP","percent":0,"count":0},{"abbr":"TOP 09","percent":0.18508997429305912,"count":72},{"abbr":"ES","percent":0,"count":0},{"abbr":"Suveren","percent":0.03598971722365039,"count":14},{"abbr":"ČPS","percent":0.002570694087403599,"count":1},{"abbr":"DSSS","percent":0.017994858611825194,"count":7},{"abbr":"Svobodní","percent":0.002570694087403599,"count":1},{"abbr":"KH","percent":null},{"abbr":"KČ","percent":0,"count":0},{"abbr":"PB","percent":0,"count":0},{"abbr":"ČSNS2005","percent":0,"count":0},{"abbr":"M","percent":0,"count":0},{"abbr":"HS","percent":0,"count":0}]},"4608":{"id":"580431","name":"Klášterec nad Orlicí","year":2010,"partyResults":[{"abbr":"Občané","percent":0,"count":0},{"abbr":"LIB","percent":0,"count":0},{"abbr":"VV","percent":0.08260869565217391,"count":38},{"abbr":"KONS","percent":0,"count":0},{"abbr":"ČSNS","percent":0,"count":0},{"abbr":"NP","percent":0,"count":0},{"abbr":"SPR-RSČ","percent":0,"count":0},{"abbr":"SPOZ","percent":0.043478260869565216,"count":20},{"abbr":"STOP","percent":0,"count":0},{"abbr":"TOP 09","percent":0.15,"count":69},{"abbr":"ES","percent":0,"count":0},{"abbr":"Suveren","percent":0.07391304347826087,"count":34},{"abbr":"ČPS","percent":0.010869565217391304,"count":5},{"abbr":"DSSS","percent":0.008695652173913044,"count":4},{"abbr":"Svobodní","percent":0.004347826086956522,"count":2},{"abbr":"KH","percent":null},{"abbr":"KČ","percent":0,"count":0},{"abbr":"PB","percent":0.010869565217391304,"count":5},{"abbr":"ČSNS2005","percent":0,"count":0},{"abbr":"M","percent":0,"count":0},{"abbr":"HS","percent":0,"count":0}]},"4610":{"id":"580481","name":"Králíky","year":2010,"partyResults":[{"abbr":"Občané","percent":0.0013972985561248254,"count":3},{"abbr":"LIB","percent":0,"count":0},{"abbr":"VV","percent":0.09501630181648812,"count":204},{"abbr":"KONS","percent":0,"count":0},{"abbr":"ČSNS","percent":0,"count":0},{"abbr":"NP","percent":0,"count":0},{"abbr":"SPR-RSČ","percent":0,"count":0},{"abbr":"SPOZ","percent":0.04052165812761994,"count":87},{"abbr":"STOP","percent":0.0032603632976245926,"count":7},{"abbr":"TOP 09","percent":0.12342803912435957,"count":265},{"abbr":"ES","percent":0,"count":0},{"abbr":"Suveren","percent":0.0423847228691197,"count":91},{"abbr":"ČPS","percent":0.008849557522123894,"count":19},{"abbr":"DSSS","percent":0.009781089892873778,"count":21},{"abbr":"Svobodní","percent":0.006054960409874243,"count":13},{"abbr":"KH","percent":null},{"abbr":"KČ","percent":0,"count":0},{"abbr":"PB","percent":0.006054960409874243,"count":13},{"abbr":"ČSNS2005","percent":0,"count":0},{"abbr":"M","percent":0,"count":0},{"abbr":"HS","percent":0,"count":0}]},"4616":{"id":"580571","name":"Lichkov","year":2010,"partyResults":[{"abbr":"Občané","percent":0.0071174377224199285,"count":2},{"abbr":"LIB","percent":0,"count":0},{"abbr":"VV","percent":0.10320284697508897,"count":29},{"abbr":"KONS","percent":0,"count":0},{"abbr":"ČSNS","percent":0,"count":0},{"abbr":"NP","percent":0,"count":0},{"abbr":"SPR-RSČ","percent":0,"count":0},{"abbr":"SPOZ","percent":0.03202846975088968,"count":9},{"abbr":"STOP","percent":0,"count":0},{"abbr":"TOP 09","percent":0.099644128113879,"count":28},{"abbr":"ES","percent":0,"count":0},{"abbr":"Suveren","percent":0.03202846975088968,"count":9},{"abbr":"ČPS","percent":0,"count":0},{"abbr":"DSSS","percent":0.017793594306049824,"count":5},{"abbr":"Svobodní","percent":0.0071174377224199285,"count":2},{"abbr":"KH","percent":null},{"abbr":"KČ","percent":0,"count":0},{"abbr":"PB","percent":0.0035587188612099642,"count":1},{"abbr":"ČSNS2005","percent":0,"count":0},{"abbr":"M","percent":0,"count":0},{"abbr":"HS","percent":0,"count":0}]},"4622":{"id":"580651","name":"Mladkov","year":2010,"partyResults":[{"abbr":"Občané","percent":0,"count":0},{"abbr":"LIB","percent":0,"count":0},{"abbr":"VV","percent":0.1,"count":32},{"abbr":"KONS","percent":0.003125,"count":1},{"abbr":"ČSNS","percent":0,"count":0},{"abbr":"NP","percent":0,"count":0},{"abbr":"SPR-RSČ","percent":0,"count":0},{"abbr":"SPOZ","percent":0.05625,"count":18},{"abbr":"STOP","percent":0,"count":0},{"abbr":"TOP 09","percent":0.115625,"count":37},{"abbr":"ES","percent":0,"count":0},{"abbr":"Suveren","percent":0.0125,"count":4},{"abbr":"ČPS","percent":0.021875,"count":7},{"abbr":"DSSS","percent":0.015625,"count":5},{"abbr":"Svobodní","percent":0.009375,"count":3},{"abbr":"KH","percent":null},{"abbr":"KČ","percent":0,"count":0},{"abbr":"PB","percent":0.00625,"count":2},{"abbr":"ČSNS2005","percent":0,"count":0},{"abbr":"M","percent":0,"count":0},{"abbr":"HS","percent":0,"count":0}]},"4629":{"id":"580724","name":"Orlicky","year":2010,"partyResults":[{"abbr":"Občané","percent":0,"count":0},{"abbr":"LIB","percent":0,"count":0},{"abbr":"VV","percent":0.14792899408284024,"count":25},{"abbr":"KONS","percent":0,"count":0},{"abbr":"ČSNS","percent":0,"count":0},{"abbr":"NP","percent":0,"count":0},{"abbr":"SPR-RSČ","percent":0,"count":0},{"abbr":"SPOZ","percent":0.011834319526627219,"count":2},{"abbr":"STOP","percent":0,"count":0},{"abbr":"TOP 09","percent":0.13609467455621302,"count":23},{"abbr":"ES","percent":0,"count":0},{"abbr":"Suveren","percent":0.03550295857988166,"count":6},{"abbr":"ČPS","percent":0.023668639053254437,"count":4},{"abbr":"DSSS","percent":0,"count":0},{"abbr":"Svobodní","percent":0.029585798816568046,"count":5},{"abbr":"KH","percent":null},{"abbr":"KČ","percent":0,"count":0},{"abbr":"PB","percent":0,"count":0},{"abbr":"ČSNS2005","percent":0,"count":0},{"abbr":"M","percent":0,"count":0},{"abbr":"HS","percent":0,"count":0}]},"4648":{"id":"580996","name":"Studené","year":2010,"partyResults":[{"abbr":"Občané","percent":0.014925373134328358,"count":1},{"abbr":"LIB","percent":0,"count":0},{"abbr":"VV","percent":0.13432835820895522,"count":9},{"abbr":"KONS","percent":0,"count":0},{"abbr":"ČSNS","percent":0,"count":0},{"abbr":"NP","percent":0,"count":0},{"abbr":"SPR-RSČ","percent":0,"count":0},{"abbr":"SPOZ","percent":0.029850746268656716,"count":2},{"abbr":"STOP","percent":0,"count":0},{"abbr":"TOP 09","percent":0.23880597014925373,"count":16},{"abbr":"ES","percent":0,"count":0},{"abbr":"Suveren","percent":0.029850746268656716,"count":2},{"abbr":"ČPS","percent":0.05970149253731343,"count":4},{"abbr":"DSSS","percent":0,"count":0},{"abbr":"Svobodní","percent":0,"count":0},{"abbr":"KH","percent":null},{"abbr":"KČ","percent":0,"count":0},{"abbr":"PB","percent":0,"count":0},{"abbr":"ČSNS2005","percent":0,"count":0},{"abbr":"M","percent":0,"count":0},{"abbr":"HS","percent":0,"count":0}]},"4653":{"id":"581054","name":"Techonín","year":2010,"partyResults":[{"abbr":"Občané","percent":0.0029069767441860465,"count":1},{"abbr":"LIB","percent":0,"count":0},{"abbr":"VV","percent":0.11337209302325581,"count":39},{"abbr":"KONS","percent":0,"count":0},{"abbr":"ČSNS","percent":0,"count":0},{"abbr":"NP","percent":0,"count":0},{"abbr":"SPR-RSČ","percent":0,"count":0},{"abbr":"SPOZ","percent":0.023255813953488372,"count":8},{"abbr":"STOP","percent":0.0029069767441860465,"count":1},{"abbr":"TOP 09","percent":0.10755813953488372,"count":37},{"abbr":"ES","percent":0,"count":0},{"abbr":"Suveren","percent":0.03488372093023256,"count":12},{"abbr":"ČPS","percent":0.01744186046511628,"count":6},{"abbr":"DSSS","percent":0.005813953488372093,"count":2},{"abbr":"Svobodní","percent":0.00872093023255814,"count":3},{"abbr":"KH","percent":null},{"abbr":"KČ","percent":0,"count":0},{"abbr":"PB","percent":0.00872093023255814,"count":3},{"abbr":"ČSNS2005","percent":0,"count":0},{"abbr":"M","percent":0,"count":0},{"abbr":"HS","percent":0,"count":0}]}}}