{"grid":["!#####$$$$$$$$!!!!%%%&%%%%%%%%%%%'''(((((((())*++++*,,,,,,,,,,,,","#####$$$$$$$$$!!!!%%%%%%%%%%%%%%%%''((((((((())+++++,,,,,,,,,,--","!####$$$!!$$$$!!..%%%%%%%%%%%%%%%%))))((((((())+++++,,,,,,,,,,--","!!!!!!$!!!!!!!/...%%%%%%%%%%%%%%%%))))))((((())+00000,,,,,,1,,--","!!!!!!!!!!!!!...%%%%%%%%%%%%%%%%%%%))))(((((())00000000,,,,1,,--","!!!!!!!!!!!!!...%%%%%%%%%%%%%%%%%%%)))))(()))))00000000,11,1,---","!!!!!!!!!........%%%%%%%%%%%%%%%%%%)))))))))))))0000000,1111111-","!!!!!!!!.........%%%%%%2%%%%%%%%%%%))))))))))))00000000,1111111-","!!!!!!!!!.........%%%%222222222222))))))))))))))0000000011111111","!!!!!!!!!..........%%2222222222222)))))))))))))))000000001111111","!!!33!!!!............22222222222222)))))))))))))0000000044444111","55!33!!!!............22222222222222)))))))))))000000000444444114","5553333!!............222222222222222)))))))666444000004444444114","7553333!..........888882222222222222)))))))666644444444444444114","9533333!!8...888888888882222222222226666)66666644444444444441144","9933333388888888888888888222222222266666666666644444444444444444","9933333388888888888888888:222222222666666666666444444444;4444444","933333338888888888888888:::::::::26666666666664444444444;;;44444","<<33=3==8888888888888>>8:::::::::::66666666666644444444;;;;;4444","<3333=====8888888888>>>>:::::::::::666666666666/?4;;;;;;;;;;@AA4","<3333======B8888>>>>>>>::::::::::::::::66:?6666???;;;;;;;;;;@AAA","<CC========BBB>>>>>>>>>>::::::::::::::::::????????;;;;;;;;;@@@@A","CCC=======BBBB>>>>>>>>>>>::::::::::::?????????????;;;;;;;;@@@@@A","CCC======BBBB>>>>>>D>>D>>DDD::::::::::????????????;;;;;;;;@@@@@@","CCCC===BBBBBB>>>>>>DDDDDDDDD::::::::???????????????;;;;;;;;;@@@@","CCCEEEEBBBBBBB>>>>DDDDDDDDDD::::::::???????????????;;;;;;;@@@@@@","CCCEEEEEEEBBBBBFFDDDDDDDDDDDD:::::?????????????????GGG;;;;@@@@@@","CCCEEEEEEEBBBBFFFDDDDDDDDDHH::::::????????????????GGGGG;;@@@@@@@","ECEEEEEEEEBBBFFFFDDDDDDIDHHH::::::????????????????GGGGGG;@@@@@@@","JJEEEEEKLLBBBFFFFDDIIIIIIHHH:::::????????????????MMGGGGGGGNN@@@@","JJJJEEKKLLBBFFFFFIIIIIIIHHHHHHHHHO???????????????MMGGGGGGGNN@@@@","JJJJJKKKKLLFFFFFIIIIIIIHHHHHHHHHOOO?????????????MMMMGGGGGGNNNNN@","JJKKJKKKKKLLFFFFFIIIIIIHHHHHHHHHOOOOO???PPP?????MMMMGGGGGGGNNNN@","JQKKKKKKKKLLLFLLLLIIIIHHHHHHHHHHOOOOP??PPPPP??MMMMMMMNNNNNNNNNNN","QQQKKKKKKKLLLLLLLLIIIHHHHHHHHHHHHOOPPP?PPPPP?MMMMMMMMNNNNNNNNNNN","QQQQKKKKKKLLLLLLLLIIIHHHHHRHHHHHHRPPPPPPPPPPMMMMMMMMMNNNNNNNNNNN","QQQQQSKKKKLLLLTUUUUUIHVVVRRRHHRRRPPPPP/PPPPPPPMMMMWWWWWNNNNNNNNN","QQQQQQSKKKKLLTTTTUUUVVVVRRRRRRRRRPPPPPPPPPPPPPPMMMMWWWWWNNNNNNNN","QQQQQQSSKKKTTTTTTTTTTTVVXRRRRRRRYYYPPPPPPPPPPPMMMMMWWWWWNNNNNNNN","QQQQQQSSSSSTTTTTTTTTTTXXXXXXRRYYYYYYYPPPPPPPPMMMMMMMWWWWNNNNNNNN","QQQQQQQSSSZZTTTT[[[TTTTXXXXXXXYYYYYYYYPPPPPMMMMMMMMMWWW]]]]NNNNN","QQQQQQSSSSZZTTTT[[[[[[[XXXXXXYYYYY^^^YYYYY^^^____MWWW]]]]]]]NNNN","QQQQQQSSSSZZZZZ[[[[[[[[XXXXXXYYYYY^^^^^^^^^^______WW/]]]]]]]]NNN","QQQQQQSSSSZZZZZ[[[[[[[[[XXXXYYYYYY^^^^^^^^^^_______W__]]]]]]]]NN","QQQQQQQQQSZZZZZ[[[[[[[[[[XXXXYYYYY^^^^^^^^^^___________]]]]]]]NN","QQQQQQQQQZZZZZZ[[[[[[[[[``XXXXYYYY^^^^^^^^^^____________]]]]]NNN","QQQQQQQQZZZZZ[[[[[[[[[`````XXXYYYY^^^^^^^^^________________]]NNN","QQQQQQaZZZZZZ[[[[[[````````XXXbbYY^^^^^^^^c_________________NNNN","QQQQaaaaZZZZ[[[[[[``````````XXbbbbbbdddccccc_______________NNNee","QQQQaaaaZZZ[[[[[[````````````bbbbbbbddddddccc_____c_______NNeeee","QQQQaaaZZZZZ[[[[[```````````fbbbbbbdddddddccccccccc________Neeee","QQQaaaaZZZZZZggggg````````hhfffbbbbbddcddccccccccc_______iieeeee","QQaaaaaaZZZZZggggggg```hhhhffffffbbbbccccccccccccccjjkk___ieeeee","lQaaaaaaZZZggggggggmmmmhhhhfffffffbbccccccccccccccjjkkkk_iiieeee","lnannnnnZZgggggggggmmmmhhhhhffffffbcccccccccccccccjjkkkkkkiiieii","nnnnnnnngZgggggggggmmmmhhhhhffofffffffppcccpcccccjjjkkkkkkiiiiii","nnnnnnnngggggggggggmmmmmhhhhooooooffffppppppppccjjjjjjjkkkkiiiii","nnnnnnnnnggggggggggmmmmmhhhhooooooofffppppppppcjjjjjjjqqqkkiiiii","nnnnnnnnnggggggggggmmmmmhhhhoooooooofoorpppppppjjjjjqqqqqqkkiiii","nnnnnnnnnsssssstttgmmtttthhhhooooooooorrrrrrrrjjjjjjjqqqqqkkkiii","nnnnnnnnssssssstttttttttuuuuuuuuooooovrrrrrrrrjjjjjjjqqqqqqiiiii","nwnnnnnxssssssssstttttttuuuuuuuuuuooovvrrrrrrrrrrjjjjjqqqqiiiiii","wwwnxxxxxssssssssytttttttuuuuuuuuuuoovvrrrrrrrrrrrjjjjqqqqiiiiii","wwwxxxxxxssssssssyytttttttuuuuuuuuuovvvrrrrrrrrrrrjjjjqqqqzziiii"],"keys":["0","1076","26","1109","1057","1990","4078","807","1064","4079","3909","3805","3783","1047",0,"3710","4008","784","1128","3757","6224","1114","1095","1043","6226","1082","3746","6223","828","945","1037","3755","3810","1124","1040","6220","831","1113","3739","1091","6222","1075","1097","1090","3742","3720","1044","2205","1102","1051","1056","1089","1129","1065","3767","1045","1137","1078","1092","3759","836","731","1111","6227","189","701","184","3726","692","721","673","4192","718","4231","1115","725","1101","3859","191","4176","681","722","694","660","656","720","690","653","4217"],"data":{"0":null,"26":{"id":"503410","name":"Žitovlice","year":"2006","partyResults":[[{"abbr":"ODS","percent":0.2558139534883721,"count":22},{"abbr":"SZ","percent":0.08139534883720931,"count":7},{"abbr":"KDU-ČSL","percent":0.05813953488372093,"count":5}],[{"abbr":"ČSSD","percent":0.4069767441860465,"count":35},{"abbr":"KSČM","percent":0.11627906976744186,"count":10}]]},"184":{"id":"513181","name":"Dománovice","year":"2006","partyResults":[[{"abbr":"ODS","percent":0.3548387096774194,"count":22},{"abbr":"SZ","percent":0.06451612903225806,"count":4},{"abbr":"KDU-ČSL","percent":0.0967741935483871,"count":6}],[{"abbr":"ČSSD","percent":0.1935483870967742,"count":12},{"abbr":"KSČM","percent":0.24193548387096775,"count":15}]]},"189":{"id":"513237","name":"Polní Chrcice","year":"2006","partyResults":[[{"abbr":"ODS","percent":0.34,"count":34},{"abbr":"SZ","percent":0.06,"count":6},{"abbr":"KDU-ČSL","percent":0.05,"count":5}],[{"abbr":"ČSSD","percent":0.29,"count":29},{"abbr":"KSČM","percent":0.13,"count":13}]]},"191":{"id":"513270","name":"Lipec","year":"2006","partyResults":[[{"abbr":"ODS","percent":0.1623931623931624,"count":19},{"abbr":"SZ","percent":0.09401709401709402,"count":11},{"abbr":"KDU-ČSL","percent":0.02564102564102564,"count":3}],[{"abbr":"ČSSD","percent":0.4188034188034188,"count":49},{"abbr":"KSČM","percent":0.21367521367521367,"count":25}]]},"653":{"id":"533165","name":"Kolín","year":"2006","partyResults":[[{"abbr":"ODS","percent":0.38499937601397727,"count":6170},{"abbr":"SZ","percent":0.057469112691875705,"count":921},{"abbr":"KDU-ČSL","percent":0.03569200049918882,"count":572}],[{"abbr":"ČSSD","percent":0.33277174591289155,"count":5333},{"abbr":"KSČM","percent":0.11980531636091352,"count":1920}]]},"656":{"id":"533190","name":"Belušice","year":"2006","partyResults":[[{"abbr":"ODS","percent":0.3063063063063063,"count":34},{"abbr":"SZ","percent":0.07207207207207207,"count":8},{"abbr":"KDU-ČSL","percent":0.02702702702702703,"count":3}],[{"abbr":"ČSSD","percent":0.4594594594594595,"count":51},{"abbr":"KSČM","percent":0.0990990990990991,"count":11}]]},"660":{"id":"533238","name":"Býchory","year":"2006","partyResults":[[{"abbr":"ODS","percent":0.39862542955326463,"count":116},{"abbr":"SZ","percent":0.044673539518900345,"count":13},{"abbr":"KDU-ČSL","percent":0.03436426116838488,"count":10}],[{"abbr":"ČSSD","percent":0.2920962199312715,"count":85},{"abbr":"KSČM","percent":0.14776632302405499,"count":43}]]},"673":{"id":"533360","name":"Jestrabí Lhota","year":"2006","partyResults":[[{"abbr":"ODS","percent":0.3902439024390244,"count":80},{"abbr":"SZ","percent":0.03414634146341464,"count":7},{"abbr":"KDU-ČSL","percent":0.05365853658536585,"count":11}],[{"abbr":"ČSSD","percent":0.3073170731707317,"count":63},{"abbr":"KSČM","percent":0.13658536585365855,"count":28}]]},"681":{"id":"533441","name":"Krakovany","year":"2006","partyResults":[[{"abbr":"ODS","percent":0.27672955974842767,"count":132},{"abbr":"SZ","percent":0.07756813417190776,"count":37},{"abbr":"KDU-ČSL","percent":0.1111111111111111,"count":53}],[{"abbr":"ČSSD","percent":0.3438155136268344,"count":164},{"abbr":"KSČM","percent":0.15723270440251572,"count":75}]]},"690":{"id":"533530","name":"Nová Ves I","year":"2006","partyResults":[[{"abbr":"ODS","percent":0.2638146167557932,"count":148},{"abbr":"SZ","percent":0.0570409982174688,"count":32},{"abbr":"KDU-ČSL","percent":0.053475935828877004,"count":30}],[{"abbr":"ČSSD","percent":0.37076648841354726,"count":208},{"abbr":"KSČM","percent":0.16042780748663102,"count":90}]]},"692":{"id":"533556","name":"Ohare","year":"2006","partyResults":[[{"abbr":"ODS","percent":0.2692307692307692,"count":42},{"abbr":"SZ","percent":0.038461538461538464,"count":6},{"abbr":"KDU-ČSL","percent":0.14102564102564102,"count":22}],[{"abbr":"ČSSD","percent":0.3333333333333333,"count":52},{"abbr":"KSČM","percent":0.12179487179487179,"count":19}]]},"694":{"id":"533572","name":"Ovcáry","year":"2006","partyResults":[[{"abbr":"ODS","percent":0.29846938775510207,"count":117},{"abbr":"SZ","percent":0.04846938775510204,"count":19},{"abbr":"KDU-ČSL","percent":0.04336734693877551,"count":17}],[{"abbr":"ČSSD","percent":0.38010204081632654,"count":149},{"abbr":"KSČM","percent":0.14795918367346939,"count":58}]]},"701":{"id":"533645","name":"Radovesnice II","year":"2006","partyResults":[[{"abbr":"ODS","percent":0.2524752475247525,"count":51},{"abbr":"SZ","percent":0.07920792079207921,"count":16},{"abbr":"KDU-ČSL","percent":0.0891089108910891,"count":18}],[{"abbr":"ČSSD","percent":0.3415841584158416,"count":69},{"abbr":"KSČM","percent":0.16336633663366337,"count":33}]]},"718":{"id":"533815","name":"Uhlírská Lhota","year":"2006","partyResults":[[{"abbr":"ODS","percent":0.2100456621004566,"count":46},{"abbr":"SZ","percent":0.0639269406392694,"count":14},{"abbr":"KDU-ČSL","percent":0.0684931506849315,"count":15}],[{"abbr":"ČSSD","percent":0.3881278538812785,"count":85},{"abbr":"KSČM","percent":0.1963470319634703,"count":43}]]},"720":{"id":"533831","name":"Velim","year":"2006","partyResults":[[{"abbr":"ODS","percent":0.3261065943992773,"count":361},{"abbr":"SZ","percent":0.03974706413730804,"count":44},{"abbr":"KDU-ČSL","percent":0.06865401987353206,"count":76}],[{"abbr":"ČSSD","percent":0.36585365853658536,"count":405},{"abbr":"KSČM","percent":0.11653116531165311,"count":129}]]},"721":{"id":"533840","name":"Velký Osek","year":"2006","partyResults":[[{"abbr":"ODS","percent":0.3299145299145299,"count":386},{"abbr":"SZ","percent":0.07008547008547009,"count":82},{"abbr":"KDU-ČSL","percent":0.04786324786324787,"count":56}],[{"abbr":"ČSSD","percent":0.35555555555555557,"count":416},{"abbr":"KSČM","percent":0.13162393162393163,"count":154}]]},"722":{"id":"533858","name":"Veltruby","year":"2006","partyResults":[[{"abbr":"ODS","percent":0.29927007299270075,"count":205},{"abbr":"SZ","percent":0.051094890510948905,"count":35},{"abbr":"KDU-ČSL","percent":0.049635036496350364,"count":34}],[{"abbr":"ČSSD","percent":0.33284671532846716,"count":228},{"abbr":"KSČM","percent":0.1708029197080292,"count":117}]]},"725":{"id":"533882","name":"Volárna","year":"2006","partyResults":[[{"abbr":"ODS","percent":0.2688679245283019,"count":57},{"abbr":"SZ","percent":0.02358490566037736,"count":5},{"abbr":"KDU-ČSL","percent":0.04245283018867924,"count":9}],[{"abbr":"ČSSD","percent":0.42452830188679247,"count":90},{"abbr":"KSČM","percent":0.17452830188679244,"count":37}]]},"731":{"id":"533947","name":"Žiželice","year":"2006","partyResults":[[{"abbr":"ODS","percent":0.2819672131147541,"count":172},{"abbr":"SZ","percent":0.04918032786885246,"count":30},{"abbr":"KDU-ČSL","percent":0.05245901639344262,"count":32}],[{"abbr":"ČSSD","percent":0.37540983606557377,"count":229},{"abbr":"KSČM","percent":0.17704918032786884,"count":108}]]},"784":{"id":"534471","name":"Záhornice","year":"2006","partyResults":[[{"abbr":"ODS","percent":0.3473053892215569,"count":58},{"abbr":"SZ","percent":0.041916167664670656,"count":7},{"abbr":"KDU-ČSL","percent":0.05389221556886228,"count":9}],[{"abbr":"ČSSD","percent":0.40119760479041916,"count":67},{"abbr":"KSČM","percent":0.12574850299401197,"count":21}]]},"807":{"id":"534706","name":"Chroustov","year":"2006","partyResults":[[{"abbr":"ODS","percent":0.30597014925373134,"count":41},{"abbr":"SZ","percent":0.04477611940298507,"count":6},{"abbr":"KDU-ČSL","percent":0.014925373134328358,"count":2}],[{"abbr":"ČSSD","percent":0.4253731343283582,"count":57},{"abbr":"KSČM","percent":0.15671641791044777,"count":21}]]},"828":{"id":"534919","name":"Netrebice","year":"2006","partyResults":[[{"abbr":"ODS","percent":0.4368932038834951,"count":45},{"abbr":"SZ","percent":0.02912621359223301,"count":3},{"abbr":"KDU-ČSL","percent":0.07766990291262135,"count":8}],[{"abbr":"ČSSD","percent":0.1941747572815534,"count":20},{"abbr":"KSČM","percent":0.13592233009708737,"count":14}]]},"831":{"id":"534943","name":"Kouty","year":"2006","partyResults":[[{"abbr":"ODS","percent":0.3973509933774834,"count":60},{"abbr":"SZ","percent":0.019867549668874173,"count":3},{"abbr":"KDU-ČSL","percent":0.046357615894039736,"count":7}],[{"abbr":"ČSSD","percent":0.3708609271523179,"count":56},{"abbr":"KSČM","percent":0.1456953642384106,"count":22}]]},"836":{"id":"534994","name":"Chotovice","year":"2006","partyResults":[[{"abbr":"ODS","percent":0.28440366972477066,"count":31},{"abbr":"SZ","percent":0.01834862385321101,"count":2},{"abbr":"KDU-ČSL","percent":0.05504587155963303,"count":6}],[{"abbr":"ČSSD","percent":0.3119266055045872,"count":34},{"abbr":"KSČM","percent":0.28440366972477066,"count":31}]]},"945":{"id":"536083","name":"Velenice","year":"2006","partyResults":[[{"abbr":"ODS","percent":0.4,"count":48},{"abbr":"SZ","percent":0.03333333333333333,"count":4},{"abbr":"KDU-ČSL","percent":0.03333333333333333,"count":4}],[{"abbr":"ČSSD","percent":0.2833333333333333,"count":34},{"abbr":"KSČM","percent":0.175,"count":21}]]},"1037":{"id":"537021","name":"Berunice","year":"2006","partyResults":[[{"abbr":"ODS","percent":0.25942350332594233,"count":117},{"abbr":"SZ","percent":0.05321507760532151,"count":24},{"abbr":"KDU-ČSL","percent":0.04212860310421286,"count":19}],[{"abbr":"ČSSD","percent":0.42350332594235035,"count":191},{"abbr":"KSČM","percent":0.13747228381374724,"count":62}]]},"1040":{"id":"537055","name":"Budimerice","year":"2006","partyResults":[[{"abbr":"ODS","percent":0.3432343234323432,"count":104},{"abbr":"SZ","percent":0.0594059405940594,"count":18},{"abbr":"KDU-ČSL","percent":0.06930693069306931,"count":21}],[{"abbr":"ČSSD","percent":0.33003300330033003,"count":100},{"abbr":"KSČM","percent":0.15841584158415842,"count":48}]]},"1043":{"id":"537080","name":"Cineves","year":"2006","partyResults":[[{"abbr":"ODS","percent":0.27848101265822783,"count":66},{"abbr":"SZ","percent":0.05063291139240506,"count":12},{"abbr":"KDU-ČSL","percent":0.05485232067510549,"count":13}],[{"abbr":"ČSSD","percent":0.34177215189873417,"count":81},{"abbr":"KSČM","percent":0.20675105485232068,"count":49}]]},"1044":{"id":"537098","name":"Dlouhopolsko","year":"2006","partyResults":[[{"abbr":"ODS","percent":0.4068965517241379,"count":59},{"abbr":"SZ","percent":0.07586206896551724,"count":11},{"abbr":"KDU-ČSL","percent":0.034482758620689655,"count":5}],[{"abbr":"ČSSD","percent":0.3310344827586207,"count":48},{"abbr":"KSČM","percent":0.10344827586206896,"count":15}]]},"1045":{"id":"537101","name":"Dobšice","year":"2006","partyResults":[[{"abbr":"ODS","percent":0.37719298245614036,"count":43},{"abbr":"SZ","percent":0.043859649122807015,"count":5},{"abbr":"KDU-ČSL","percent":0.043859649122807015,"count":5}],[{"abbr":"ČSSD","percent":0.2631578947368421,"count":30},{"abbr":"KSČM","percent":0.21052631578947367,"count":24}]]},"1047":{"id":"537128","name":"Dymokury","year":"2006","partyResults":[[{"abbr":"ODS","percent":0.3597733711048159,"count":127},{"abbr":"SZ","percent":0.0764872521246459,"count":27},{"abbr":"KDU-ČSL","percent":0.08498583569405099,"count":30}],[{"abbr":"ČSSD","percent":0.3002832861189802,"count":106},{"abbr":"KSČM","percent":0.1359773371104816,"count":48}]]},"1051":{"id":"537161","name":"Hradcany","year":"2006","partyResults":[[{"abbr":"ODS","percent":0.488,"count":61},{"abbr":"SZ","percent":0.056,"count":7},{"abbr":"KDU-ČSL","percent":0.04,"count":5}],[{"abbr":"ČSSD","percent":0.24,"count":30},{"abbr":"KSČM","percent":0.096,"count":12}]]},"1056":{"id":"537217","name":"Chotánky","year":"2006","partyResults":[[{"abbr":"ODS","percent":0.4247787610619469,"count":96},{"abbr":"SZ","percent":0.06637168141592921,"count":15},{"abbr":"KDU-ČSL","percent":0.030973451327433628,"count":7}],[{"abbr":"ČSSD","percent":0.3141592920353982,"count":71},{"abbr":"KSČM","percent":0.09734513274336283,"count":22}]]},"1057":{"id":"537225","name":"Chotešice","year":"2006","partyResults":[[{"abbr":"ODS","percent":0.348993288590604,"count":52},{"abbr":"SZ","percent":0.0738255033557047,"count":11},{"abbr":"KDU-ČSL","percent":0.04697986577181208,"count":7}],[{"abbr":"ČSSD","percent":0.3221476510067114,"count":48},{"abbr":"KSČM","percent":0.18120805369127516,"count":27}]]},"1064":{"id":"537292","name":"Knežice","year":"2006","partyResults":[[{"abbr":"ODS","percent":0.24738675958188153,"count":71},{"abbr":"SZ","percent":0.059233449477351915,"count":17},{"abbr":"KDU-ČSL","percent":0.059233449477351915,"count":17}],[{"abbr":"ČSSD","percent":0.4425087108013937,"count":127},{"abbr":"KSČM","percent":0.13240418118466898,"count":38}]]},"1065":{"id":"537306","name":"Kolaje","year":"2006","partyResults":[[{"abbr":"ODS","percent":0.3076923076923077,"count":16},{"abbr":"SZ","percent":0.1346153846153846,"count":7},{"abbr":"KDU-ČSL","percent":0.11538461538461539,"count":6}],[{"abbr":"ČSSD","percent":0.21153846153846154,"count":11},{"abbr":"KSČM","percent":0.19230769230769232,"count":10}]]},"1075":{"id":"537403","name":"Kreckov","year":"2006","partyResults":[[{"abbr":"ODS","percent":0.413265306122449,"count":81},{"abbr":"SZ","percent":0.04591836734693878,"count":9},{"abbr":"KDU-ČSL","percent":0.04081632653061224,"count":8}],[{"abbr":"ČSSD","percent":0.3112244897959184,"count":61},{"abbr":"KSČM","percent":0.11734693877551021,"count":23}]]},"1076":{"id":"537411","name":"Krinec","year":"2006","partyResults":[[{"abbr":"ODS","percent":0.2583941605839416,"count":177},{"abbr":"SZ","percent":0.04671532846715328,"count":32},{"abbr":"KDU-ČSL","percent":0.07883211678832117,"count":54}],[{"abbr":"ČSSD","percent":0.36934306569343067,"count":253},{"abbr":"KSČM","percent":0.1927007299270073,"count":132}]]},"1078":{"id":"537438","name":"Libice nad Cidlinou","year":"2006","partyResults":[[{"abbr":"ODS","percent":0.3215258855585831,"count":236},{"abbr":"SZ","percent":0.05858310626702997,"count":43},{"abbr":"KDU-ČSL","percent":0.043596730245231606,"count":32}],[{"abbr":"ČSSD","percent":0.3869209809264305,"count":284},{"abbr":"KSČM","percent":0.11852861035422343,"count":87}]]},"1082":{"id":"537489","name":"Mestec Králové","year":"2006","partyResults":[[{"abbr":"ODS","percent":0.3545516769336071,"count":518},{"abbr":"SZ","percent":0.07597535934291581,"count":111},{"abbr":"KDU-ČSL","percent":0.038329911019849415,"count":56}],[{"abbr":"ČSSD","percent":0.3538672142368241,"count":517},{"abbr":"KSČM","percent":0.12320328542094455,"count":180}]]},"1089":{"id":"537551","name":"Odrepsy","year":"2006","partyResults":[[{"abbr":"ODS","percent":0.4124293785310734,"count":73},{"abbr":"SZ","percent":0.07344632768361582,"count":13},{"abbr":"KDU-ČSL","percent":0.05084745762711865,"count":9}],[{"abbr":"ČSSD","percent":0.2937853107344633,"count":52},{"abbr":"KSČM","percent":0.10734463276836158,"count":19}]]},"1090":{"id":"537560","name":"Okrínek","year":"2006","partyResults":[[{"abbr":"ODS","percent":0.3125,"count":25},{"abbr":"SZ","percent":0.075,"count":6},{"abbr":"KDU-ČSL","percent":0.025,"count":2}],[{"abbr":"ČSSD","percent":0.3125,"count":25},{"abbr":"KSČM","percent":0.225,"count":18}]]},"1091":{"id":"537578","name":"Opocnice","year":"2006","partyResults":[[{"abbr":"ODS","percent":0.39344262295081966,"count":96},{"abbr":"SZ","percent":0.07377049180327869,"count":18},{"abbr":"KDU-ČSL","percent":0.05327868852459016,"count":13}],[{"abbr":"ČSSD","percent":0.319672131147541,"count":78},{"abbr":"KSČM","percent":0.10655737704918032,"count":26}]]},"1092":{"id":"537586","name":"Opolany","year":"2006","partyResults":[[{"abbr":"ODS","percent":0.3882113821138211,"count":191},{"abbr":"SZ","percent":0.0508130081300813,"count":25},{"abbr":"KDU-ČSL","percent":0.0508130081300813,"count":25}],[{"abbr":"ČSSD","percent":0.3333333333333333,"count":164},{"abbr":"KSČM","percent":0.12601626016260162,"count":62}]]},"1095":{"id":"537616","name":"Oskorínek","year":"2006","partyResults":[[{"abbr":"ODS","percent":0.2508833922261484,"count":71},{"abbr":"SZ","percent":0.04946996466431095,"count":14},{"abbr":"KDU-ČSL","percent":0.08833922261484099,"count":25}],[{"abbr":"ČSSD","percent":0.3003533568904594,"count":85},{"abbr":"KSČM","percent":0.22614840989399293,"count":64}]]},"1097":{"id":"537632","name":"Pátek","year":"2006","partyResults":[[{"abbr":"ODS","percent":0.547112462006079,"count":180},{"abbr":"SZ","percent":0.0425531914893617,"count":14},{"abbr":"KDU-ČSL","percent":0.057750759878419454,"count":19}],[{"abbr":"ČSSD","percent":0.23100303951367782,"count":76},{"abbr":"KSČM","percent":0.04559270516717325,"count":15}]]},"1101":{"id":"537675","name":"Pnov-Predhradí","year":"2006","partyResults":[[{"abbr":"ODS","percent":0.2918149466192171,"count":82},{"abbr":"SZ","percent":0.042704626334519574,"count":12},{"abbr":"KDU-ČSL","percent":0.08896797153024912,"count":25}],[{"abbr":"ČSSD","percent":0.4199288256227758,"count":118},{"abbr":"KSČM","percent":0.11387900355871886,"count":32}]]},"1102":{"id":"537683","name":"Podebrady","year":"2006","partyResults":[[{"abbr":"ODS","percent":0.4624984400349432,"count":3706},{"abbr":"SZ","percent":0.07188318981654811,"count":576},{"abbr":"KDU-ČSL","percent":0.046674154498939226,"count":374}],[{"abbr":"ČSSD","percent":0.27542743042555845,"count":2207},{"abbr":"KSČM","percent":0.08086858854361663,"count":648}]]},"1109":{"id":"537756","name":"Roždalovice","year":"2006","partyResults":[[{"abbr":"ODS","percent":0.3803191489361702,"count":286},{"abbr":"SZ","percent":0.04654255319148936,"count":35},{"abbr":"KDU-ČSL","percent":0.07180851063829788,"count":54}],[{"abbr":"ČSSD","percent":0.30319148936170215,"count":228},{"abbr":"KSČM","percent":0.125,"count":94}]]},"1111":{"id":"537772","name":"Sány","year":"2006","partyResults":[[{"abbr":"ODS","percent":0.3386454183266932,"count":85},{"abbr":"SZ","percent":0.05179282868525897,"count":13},{"abbr":"KDU-ČSL","percent":0.05976095617529881,"count":15}],[{"abbr":"ČSSD","percent":0.33067729083665337,"count":83},{"abbr":"KSČM","percent":0.09561752988047809,"count":24}]]},"1113":{"id":"537799","name":"Senice","year":"2006","partyResults":[[{"abbr":"ODS","percent":0.3181818181818182,"count":35},{"abbr":"SZ","percent":0.045454545454545456,"count":5},{"abbr":"KDU-ČSL","percent":0.02727272727272727,"count":3}],[{"abbr":"ČSSD","percent":0.41818181818181815,"count":46},{"abbr":"KSČM","percent":0.12727272727272726,"count":14}]]},"1114":{"id":"537802","name":"Slovec","year":"2006","partyResults":[[{"abbr":"ODS","percent":0.286231884057971,"count":79},{"abbr":"SZ","percent":0.050724637681159424,"count":14},{"abbr":"KDU-ČSL","percent":0.036231884057971016,"count":10}],[{"abbr":"ČSSD","percent":0.40217391304347827,"count":111},{"abbr":"KSČM","percent":0.16666666666666666,"count":46}]]},"1115":{"id":"537811","name":"Sokolec","year":"2006","partyResults":[[{"abbr":"ODS","percent":0.3416289592760181,"count":151},{"abbr":"SZ","percent":0.05203619909502263,"count":23},{"abbr":"KDU-ČSL","percent":0.04524886877828054,"count":20}],[{"abbr":"ČSSD","percent":0.38687782805429866,"count":171},{"abbr":"KSČM","percent":0.1085972850678733,"count":48}]]},"1124":{"id":"537900","name":"Úmyslovice","year":"2006","partyResults":[[{"abbr":"ODS","percent":0.34306569343065696,"count":47},{"abbr":"SZ","percent":0.10948905109489052,"count":15},{"abbr":"KDU-ČSL","percent":0.029197080291970802,"count":4}],[{"abbr":"ČSSD","percent":0.40875912408759124,"count":56},{"abbr":"KSČM","percent":0.058394160583941604,"count":8}]]},"1128":{"id":"537942","name":"Vestec","year":"2006","partyResults":[[{"abbr":"ODS","percent":0.22875816993464052,"count":35},{"abbr":"SZ","percent":0.05228758169934641,"count":8},{"abbr":"KDU-ČSL","percent":0.0784313725490196,"count":12}],[{"abbr":"ČSSD","percent":0.45751633986928103,"count":70},{"abbr":"KSČM","percent":0.13725490196078433,"count":21}]]},"1129":{"id":"537951","name":"Vlkov pod Oškobrhem","year":"2006","partyResults":[[{"abbr":"ODS","percent":0.4166666666666667,"count":25},{"abbr":"SZ","percent":0.08333333333333333,"count":5},{"abbr":"KDU-ČSL","percent":0.03333333333333333,"count":2}],[{"abbr":"ČSSD","percent":0.3333333333333333,"count":20},{"abbr":"KSČM","percent":0.11666666666666667,"count":7}]]},"1137":{"id":"538035","name":"Žehun","year":"2006","partyResults":[[{"abbr":"ODS","percent":0.29739776951672864,"count":80},{"abbr":"SZ","percent":0.040892193308550186,"count":11},{"abbr":"KDU-ČSL","percent":0.022304832713754646,"count":6}],[{"abbr":"ČSSD","percent":0.42379182156133827,"count":114},{"abbr":"KSČM","percent":0.15613382899628253,"count":42}]]},"1990":{"id":"548952","name":"Budceves","year":"2006","partyResults":[[{"abbr":"ODS","percent":0.3493975903614458,"count":29},{"abbr":"SZ","percent":0.03614457831325301,"count":3},{"abbr":"KDU-ČSL","percent":0.04819277108433735,"count":4}],[{"abbr":"ČSSD","percent":0.2289156626506024,"count":19},{"abbr":"KSČM","percent":0.26506024096385544,"count":22}]]},"2205":{"id":"551481","name":"Knežicky","year":"2006","partyResults":[[{"abbr":"ODS","percent":0.4339622641509434,"count":46},{"abbr":"SZ","percent":0.09433962264150944,"count":10},{"abbr":"KDU-ČSL","percent":0.04716981132075472,"count":5}],[{"abbr":"ČSSD","percent":0.24528301886792453,"count":26},{"abbr":"KSČM","percent":0.0660377358490566,"count":7}]]},"3710":{"id":"570001","name":"Hlušice","year":"2006","partyResults":[[{"abbr":"ODS","percent":0.31986531986531985,"count":95},{"abbr":"SZ","percent":0.04377104377104377,"count":13},{"abbr":"KDU-ČSL","percent":0.05723905723905724,"count":17}],[{"abbr":"ČSSD","percent":0.30303030303030304,"count":90},{"abbr":"KSČM","percent":0.16161616161616163,"count":48}]]},"3720":{"id":"570109","name":"Chlumec nad Cidlinou","year":"2006","partyResults":[[{"abbr":"ODS","percent":0.33321714883234577,"count":956},{"abbr":"SZ","percent":0.05995120250958522,"count":172},{"abbr":"KDU-ČSL","percent":0.09132101777622866,"count":262}],[{"abbr":"ČSSD","percent":0.3405367723945626,"count":977},{"abbr":"KSČM","percent":0.12757058208434996,"count":366}]]},"3726":{"id":"570168","name":"Klamoš","year":"2006","partyResults":[[{"abbr":"ODS","percent":0.32083333333333336,"count":77},{"abbr":"SZ","percent":0.05,"count":12},{"abbr":"KDU-ČSL","percent":0.020833333333333332,"count":5}],[{"abbr":"ČSSD","percent":0.375,"count":90},{"abbr":"KSČM","percent":0.175,"count":42}]]},"3739":{"id":"570290","name":"Lišice","year":"2006","partyResults":[[{"abbr":"ODS","percent":0.17,"count":17},{"abbr":"SZ","percent":0.05,"count":5},{"abbr":"KDU-ČSL","percent":0.19,"count":19}],[{"abbr":"ČSSD","percent":0.38,"count":38},{"abbr":"KSČM","percent":0.16,"count":16}]]},"3742":{"id":"570320","name":"Lovcice","year":"2006","partyResults":[[{"abbr":"ODS","percent":0.29754601226993865,"count":97},{"abbr":"SZ","percent":0.02147239263803681,"count":7},{"abbr":"KDU-ČSL","percent":0.07668711656441718,"count":25}],[{"abbr":"ČSSD","percent":0.450920245398773,"count":147},{"abbr":"KSČM","percent":0.1196319018404908,"count":39}]]},"3746":{"id":"570362","name":"Lužec nad Cidlinou","year":"2006","partyResults":[[{"abbr":"ODS","percent":0.3464566929133858,"count":88},{"abbr":"SZ","percent":0.051181102362204724,"count":13},{"abbr":"KDU-ČSL","percent":0.027559055118110236,"count":7}],[{"abbr":"ČSSD","percent":0.3937007874015748,"count":100},{"abbr":"KSČM","percent":0.12992125984251968,"count":33}]]},"3755":{"id":"570478","name":"Nepolisy","year":"2006","partyResults":[[{"abbr":"ODS","percent":0.240990990990991,"count":107},{"abbr":"SZ","percent":0.04504504504504504,"count":20},{"abbr":"KDU-ČSL","percent":0.02252252252252252,"count":10}],[{"abbr":"ČSSD","percent":0.4369369369369369,"count":194},{"abbr":"KSČM","percent":0.16441441441441443,"count":73}]]},"3757":{"id":"570508","name":"Nový Bydžov","year":"2006","partyResults":[[{"abbr":"ODS","percent":0.3393939393939394,"count":1176},{"abbr":"SZ","percent":0.06464646464646465,"count":224},{"abbr":"KDU-ČSL","percent":0.046176046176046176,"count":160}],[{"abbr":"ČSSD","percent":0.3486291486291486,"count":1208},{"abbr":"KSČM","percent":0.1367965367965368,"count":474}]]},"3759":{"id":"570524","name":"Olešnice","year":"2006","partyResults":[[{"abbr":"ODS","percent":0.35064935064935066,"count":54},{"abbr":"SZ","percent":0.09090909090909091,"count":14},{"abbr":"KDU-ČSL","percent":0.05194805194805195,"count":8}],[{"abbr":"ČSSD","percent":0.3246753246753247,"count":50},{"abbr":"KSČM","percent":0.13636363636363635,"count":21}]]},"3767":{"id":"570681","name":"Prevýšov","year":"2006","partyResults":[[{"abbr":"ODS","percent":0.3314917127071823,"count":60},{"abbr":"SZ","percent":0.04419889502762431,"count":8},{"abbr":"KDU-ČSL","percent":0.09392265193370165,"count":17}],[{"abbr":"ČSSD","percent":0.3701657458563536,"count":67},{"abbr":"KSČM","percent":0.11602209944751381,"count":21}]]},"3783":{"id":"570869","name":"Smidary","year":"2006","partyResults":[[{"abbr":"ODS","percent":0.25806451612903225,"count":184},{"abbr":"SZ","percent":0.04067321178120617,"count":29},{"abbr":"KDU-ČSL","percent":0.03506311360448808,"count":25}],[{"abbr":"ČSSD","percent":0.34782608695652173,"count":248},{"abbr":"KSČM","percent":0.23422159887798036,"count":167}]]},"3805":{"id":"571083","name":"Vinary","year":"2006","partyResults":[[{"abbr":"ODS","percent":0.23484848484848486,"count":62},{"abbr":"SZ","percent":0.06060606060606061,"count":16},{"abbr":"KDU-ČSL","percent":0.08712121212121213,"count":23}],[{"abbr":"ČSSD","percent":0.36363636363636365,"count":96},{"abbr":"KSČM","percent":0.17424242424242425,"count":46}]]},"3810":{"id":"571130","name":"Zachraštany","year":"2006","partyResults":[[{"abbr":"ODS","percent":0.29473684210526313,"count":28},{"abbr":"SZ","percent":0.042105263157894736,"count":4},{"abbr":"KDU-ČSL","percent":0.042105263157894736,"count":4}],[{"abbr":"ČSSD","percent":0.2736842105263158,"count":26},{"abbr":"KSČM","percent":0.25263157894736843,"count":24}]]},"3859":{"id":"571636","name":"Nemcice","year":"2006","partyResults":[[{"abbr":"ODS","percent":0.3352941176470588,"count":57},{"abbr":"SZ","percent":0.058823529411764705,"count":10},{"abbr":"KDU-ČSL","percent":0.047058823529411764,"count":8}],[{"abbr":"ČSSD","percent":0.35294117647058826,"count":60},{"abbr":"KSČM","percent":0.17647058823529413,"count":30}]]},"3909":{"id":"572144","name":"Sekerice","year":"2006","partyResults":[[{"abbr":"ODS","percent":0.24358974358974358,"count":19},{"abbr":"SZ","percent":0.038461538461538464,"count":3},{"abbr":"KDU-ČSL","percent":0.038461538461538464,"count":3}],[{"abbr":"ČSSD","percent":0.358974358974359,"count":28},{"abbr":"KSČM","percent":0.23076923076923078,"count":18}]]},"4008":{"id":"573132","name":"Starý Bydžov","year":"2006","partyResults":[[{"abbr":"ODS","percent":0.3225806451612903,"count":60},{"abbr":"SZ","percent":0.043010752688172046,"count":8},{"abbr":"KDU-ČSL","percent":0.04838709677419355,"count":9}],[{"abbr":"ČSSD","percent":0.40860215053763443,"count":76},{"abbr":"KSČM","percent":0.12365591397849462,"count":23}]]},"4078":{"id":"573841","name":"Židovice","year":"2006","partyResults":[[{"abbr":"ODS","percent":0.1527777777777778,"count":11},{"abbr":"SZ","percent":0.06944444444444445,"count":5},{"abbr":"KDU-ČSL","percent":0.013888888888888888,"count":1}],[{"abbr":"ČSSD","percent":0.5,"count":36},{"abbr":"KSČM","percent":0.18055555555555555,"count":13}]]},"4079":{"id":"573850","name":"Žlunice","year":"2006","partyResults":[[{"abbr":"ODS","percent":0.25874125874125875,"count":37},{"abbr":"SZ","percent":0.013986013986013986,"count":2},{"abbr":"KDU-ČSL","percent":0.04895104895104895,"count":7}],[{"abbr":"ČSSD","percent":0.48951048951048953,"count":70},{"abbr":"KSČM","percent":0.18181818181818182,"count":26}]]},"4176":{"id":"574961","name":"Hlavecník","year":"2006","partyResults":[[{"abbr":"ODS","percent":0.304,"count":38},{"abbr":"SZ","percent":0.032,"count":4},{"abbr":"KDU-ČSL","percent":0.024,"count":3}],[{"abbr":"ČSSD","percent":0.376,"count":47},{"abbr":"KSČM","percent":0.248,"count":31}]]},"4192":{"id":"575178","name":"Kladruby nad Labem","year":"2006","partyResults":[[{"abbr":"ODS","percent":0.216,"count":81},{"abbr":"SZ","percent":0.058666666666666666,"count":22},{"abbr":"KDU-ČSL","percent":0.02666666666666667,"count":10}],[{"abbr":"ČSSD","percent":0.36,"count":135},{"abbr":"KSČM","percent":0.25333333333333335,"count":95}]]},"4217":{"id":"575615","name":"Selmice","year":"2006","partyResults":[[{"abbr":"ODS","percent":0.22388059701492538,"count":15},{"abbr":"SZ","percent":0.1044776119402985,"count":7},{"abbr":"KDU-ČSL","percent":0,"count":0}],[{"abbr":"ČSSD","percent":0.2537313432835821,"count":17},{"abbr":"KSČM","percent":0.373134328358209,"count":25}]]},"4231":{"id":"575810","name":"Tetov","year":"2006","partyResults":[[{"abbr":"ODS","percent":0.1919191919191919,"count":19},{"abbr":"SZ","percent":0.050505050505050504,"count":5},{"abbr":"KDU-ČSL","percent":0.020202020202020204,"count":2}],[{"abbr":"ČSSD","percent":0.41414141414141414,"count":41},{"abbr":"KSČM","percent":0.2828282828282828,"count":28}]]},"6220":{"id":"599590","name":"Podmoky","year":"2006","partyResults":[[{"abbr":"ODS","percent":0.29411764705882354,"count":30},{"abbr":"SZ","percent":0.049019607843137254,"count":5},{"abbr":"KDU-ČSL","percent":0.06862745098039216,"count":7}],[{"abbr":"ČSSD","percent":0.3627450980392157,"count":37},{"abbr":"KSČM","percent":0.1568627450980392,"count":16}]]},"6222":{"id":"599611","name":"Vrbice","year":"2006","partyResults":[[{"abbr":"ODS","percent":0.3627450980392157,"count":37},{"abbr":"SZ","percent":0.049019607843137254,"count":5},{"abbr":"KDU-ČSL","percent":0.14705882352941177,"count":15}],[{"abbr":"ČSSD","percent":0.24509803921568626,"count":25},{"abbr":"KSČM","percent":0.1568627450980392,"count":16}]]},"6223":{"id":"599620","name":"Chleby","year":"2006","partyResults":[[{"abbr":"ODS","percent":0.44505494505494503,"count":81},{"abbr":"SZ","percent":0.07142857142857142,"count":13},{"abbr":"KDU-ČSL","percent":0.03296703296703297,"count":6}],[{"abbr":"ČSSD","percent":0.24175824175824176,"count":44},{"abbr":"KSČM","percent":0.13736263736263737,"count":25}]]},"6224":{"id":"599638","name":"Hrubý Jeseník","year":"2006","partyResults":[[{"abbr":"ODS","percent":0.2425531914893617,"count":57},{"abbr":"SZ","percent":0.07659574468085106,"count":18},{"abbr":"KDU-ČSL","percent":0.0851063829787234,"count":20}],[{"abbr":"ČSSD","percent":0.40425531914893614,"count":95},{"abbr":"KSČM","percent":0.11063829787234042,"count":26}]]},"6226":{"id":"599654","name":"Nový Dvur","year":"2006","partyResults":[[{"abbr":"ODS","percent":0.3,"count":15},{"abbr":"SZ","percent":0.1,"count":5},{"abbr":"KDU-ČSL","percent":0.1,"count":5}],[{"abbr":"ČSSD","percent":0.26,"count":13},{"abbr":"KSČM","percent":0.2,"count":10}]]},"6227":{"id":"599662","name":"Osecek","year":"2006","partyResults":[[{"abbr":"ODS","percent":0.3870967741935484,"count":24},{"abbr":"SZ","percent":0.016129032258064516,"count":1},{"abbr":"KDU-ČSL","percent":0.016129032258064516,"count":1}],[{"abbr":"ČSSD","percent":0.43548387096774194,"count":27},{"abbr":"KSČM","percent":0.11290322580645161,"count":7}]]}}}