{"grid":["!!!!!!!###########$$$##%&&&&&&''''(((((((()))))))))*******+++++,","!!!!!!!!##########$$###&&&&&&&'''((((((((())))))))********+++,,,","!!!!!!!################&&&&&&'''''(((((((()))))))))*******+++,,,","!!!!!!#################&&&&&&&'''%(((((((())))))))))*******,,,,,","!!!!!!!################&&&&&--''''((((((((())))))))********,,,,,","!!!!!!...##############&&&----'''((((((((()))))))))********,,,,,",".!!!!....###############&-----'''''((((((())))))))))******,,,///",".!!!.....###############-------''''''(((((()))))))))*******,,///",".........##############0---------''''(((((()))))))*********/////","..........#############00---------'''(((((1))))))********///////","..........###########000000--------'''(((())))))))*******///////",".........###########00000000------''''(((11))))))))******///////",".......############0000000000----''''((((11)))))********////////","...################0000000000----'''''''(11))))*********//2/////",".#################00000000000----'''''''1111)))*********%222////","##################000000000000---''''''''1111))*********32222222","##################0000000000000---'''''''1111111*******332222222","##################00000000000000--'''''''11111111*****3332222222","##################000000000000000-'''''''1111111111**33333332222","#################0000000000000000000''''''1111111111333333333344","################500000000000000000000''''''111111111333333333344","###############5555000000000000000000'''''''''111166633333333444","###7##7777####55555500000000000000000''''''''''11166663333334444","#777777777####55555550000000000000000''''''''''66666688833333444","7777777777###555555550000000000000000'''''''''''6666888888333444","777777777###555555555550000000000000'''''''''''96668888888834444","777777777###55555555555:::::00000000'''''''''9999968888888844444","777777777#5555555555555:::::::000000''''''''9999998888888;444444","7777777775555::::55555555:::::::<<==='''''9999999988888888;;4444","777777777::::::::::55555::::::::<<=========9999999%8888;;;;;;444","77777777::::::::::::::55:::::::<<<<========999999999;88;;;;;;;4>","77777777:::::::::::::::::::::<<<<<<========999999999;;;;;;;;;;;4","77777777::::::::::::::::::::<<<<<========?????999999;;;;;;;;;;;;","77777777::::::::::::::::::::<<<<<=======????????999999;;;;;;;;;;","77777777::::::::::::::::::::<<<<========?????????@@@@AA;;;;;;;;;","7777777777::::::::::::::BBBBB<<<<<=======???????@@@@@AAAAAA;;;;;","7777777777::::::::::::::BBBBB<<<<<=<<<<<???????@@@@@@@AAAAAAAA;;","7777777777:::::CC:::::::BBBBB<<<<<<<<<<<<<??@@@@@@@@@@AAAAAAAAA>","7777777777:::::CCC::::::BBBBB<<<<<<<<<<DDDDD@@@@@@@@@@AAAAAAAAA>","77777777777::::CCCC:::::BBBBB<<<<<<<<<DDDDDDD@@@@@@@@@AAAAAAAAAA","7EEEE777777CCCCCCCCCC:::B<<<B<<<<<<<<<DDDDDDDD@@@@@@@@AAAAAAFFFF","EEEEE777777CCCCCCCCCCC:B<<<<B<<<<<<<<DDDDDDDDDD@@@@@@@AAAAAFFFFF","EEEEEE7777CCCCCCCCCCCCCB<<<<<<<<<<DDDDDDDDDDDDDD@@@@@@AAAAAFFFFF","EEEEEE77::CCCCCCCCCCCCCC<<<<<<<<<GDDDDDDDDDDDDDDD@@@@@@AAFFFFFFF","EEEEEH::::::CCCCCCCCCCCC<<<<<<<<GGDGGDDDDDDDDDDDDI@@@@@AAFFFFFFF","EEEHHHH::::::CCCCCCCJCCC<JJJ<<<GGGGGGDDDDDDDDDDDIIIII@@FFFFFFFFF","EEHHHHH::::::CCCCCCCJJJJJJJJGGGGGGGGGDKKDDDDDDDDIIIIIII@FFFFFFFF","EEEHHHH:::::CCCCCCCCJJJJJJJJGGGGGGGGGKKKKLLDDDDIIIIIIII@MFFFFFFF","EEHHHHH:::::CCCCCCCCJJJJJJJJGGGGGGGGGKKKLLLLLDIIIIIIIIIIMMMNNNFF","HHHHHHH::::::CCCCCCCJJJJJJJJGGGGGGGGGKKKLLLLLLIIIIIIIIIMMMMNNNNN","HHHHHHH::::::::CCCCJJJJJJJJJJGGGGGGGGKKLLLLLLLLLIIIMMMMMMMMNNNNN","HHHHHHH:::::OOOCCCCJJJJJJJJJJGGGGGGGGKKLLLLLLLLLMMMMMMMMMMMNNNNN","HHHHHHH:::::OOOJJCJJJJJJJJJJJJGGGGGGKKLLLLLLLLLLPPMMMMMMMMMMNNNN","HHHHHHHHH::OOOJJJJJJJJJJJJJJJJJGGGGGKGLLLLLLLLLLPPPMMMMMMMMMNNNN","HHHHHHHHHOOOOOOOJJJJJJJJJJJJJJJJGGGGGGGLLLLLLPLPPPPPMMMMMMMMNNNN","HHHHHHHHHOOOOOOOOJJJJJJJJJJJJJJJJGGGGGLLLLLLLPPPPPPMMMMMMMMNNQQN","RSHHHHHHHOOOOOOOJJJJJJJJJJJJJJJJJGGGGGLLLLTTPPPPPPPMMMMMMMMQQQQQ","SSHHHHHH%OOOOOOOJJJJJJJJJJUJJJJJJGGGGGGTTTTTPPPPPPPPMMMMMMMQQQQQ","SSHHHHHVVOOOOOOOJJJUUUUUUUUUUJJJJGGWGGTTTTTTTPPPPPPPPMMMMMMQQQQQ","SSHHXXVVVVVOOOOOJUUUUUUUUUUUUJJJJWWWGGTTTTTTPPPPPYYYYMMMMMMQQQQQ","SXXXXXVVVVVOOOOUUUUUUUUUUUUUUUUUJJWWWG%TTTTTTTTPPYYYYYZZMMMQQQQQ","SXXXXXVVVVVVV[[UUUUUUUUUUUUUUUUWWWWWWWW]]]]T]TTYYYYYYYZZZMMQQQQQ","SXXXXXVVVVVVV[[[UUUU[[UUUUUUUUWWWWWWW]]]]]]]]^^^YYYYYYYZZ_QQQ___","SXXXXXVVVVVV[[[[[[U[[[[UUUUUUUUWWWWWW]]]]]]]]^^^^YYYYYYZZ__QQ___"],"keys":["0","3108","3421","398",0,"3457","3405","3380","3395","3444","3400","3383","3398","3390","3417","3365","3374","3377","1492","1514","3412","3291","3452","1509","1544","3391","1515","1475","3282","1498","1474","1489","1483","3283","3416","1491","3403","1521","1522","3363","3290","1485","3296","1527","1536","1467","6119","1546","1505","2755","2767","3314","314","4490","312","3437","1524","1526","6120","3315","1559","1535"],"data":{"0":null,"312":{"id":"529699","name":"Velká Chmelištná","year":2013,"partyResults":[{"abbr":"ANO 2011","percent":0.10869565217391304,"count":5}]},"314":{"id":"529711","name":"Drahouš","year":2013,"partyResults":[{"abbr":"ANO 2011","percent":0.20512820512820512,"count":8}]},"398":{"id":"530581","name":"Ceradice","year":2013,"partyResults":[{"abbr":"ANO 2011","percent":0.25196850393700787,"count":32}]},"1467":{"id":"541656","name":"Rakovník","year":2013,"partyResults":[{"abbr":"ANO 2011","percent":0.18572364112639161,"count":1418}]},"1474":{"id":"541729","name":"Horesedly","year":2013,"partyResults":[{"abbr":"ANO 2011","percent":0.1978021978021978,"count":36}]},"1475":{"id":"541737","name":"Horovicky","year":2013,"partyResults":[{"abbr":"ANO 2011","percent":0.13609467455621302,"count":23}]},"1483":{"id":"541818","name":"Chráštany","year":2013,"partyResults":[{"abbr":"ANO 2011","percent":0.22297297297297297,"count":66}]},"1485":{"id":"541834","name":"Jesenice","year":2013,"partyResults":[{"abbr":"ANO 2011","percent":0.1601796407185629,"count":107}]},"1489":{"id":"541877","name":"Kneževes","year":2013,"partyResults":[{"abbr":"ANO 2011","percent":0.20286396181384247,"count":85}]},"1491":{"id":"541893","name":"Kolešovice","year":2013,"partyResults":[{"abbr":"ANO 2011","percent":0.16939890710382513,"count":62}]},"1492":{"id":"541907","name":"Kounov","year":2013,"partyResults":[{"abbr":"ANO 2011","percent":0.14814814814814814,"count":28}]},"1498":{"id":"541966","name":"Krupá","year":2013,"partyResults":[{"abbr":"ANO 2011","percent":0.20408163265306123,"count":40}]},"1505":{"id":"542032","name":"Lubná","year":2013,"partyResults":[{"abbr":"ANO 2011","percent":0.16294642857142858,"count":73}]},"1509":{"id":"542075","name":"Milostín","year":2013,"partyResults":[{"abbr":"ANO 2011","percent":0.20491803278688525,"count":25}]},"1514":{"id":"542121","name":"Mutejovice","year":2013,"partyResults":[{"abbr":"ANO 2011","percent":0.2732732732732733,"count":91}]},"1515":{"id":"542130","name":"Nesuchyne","year":2013,"partyResults":[{"abbr":"ANO 2011","percent":0.16279069767441862,"count":28}]},"1521":{"id":"542199","name":"Olešná","year":2013,"partyResults":[{"abbr":"ANO 2011","percent":0.18095238095238095,"count":57}]},"1522":{"id":"542202","name":"Orácov","year":2013,"partyResults":[{"abbr":"ANO 2011","percent":0.1715210355987055,"count":53}]},"1524":{"id":"542229","name":"Petrovice","year":2013,"partyResults":[{"abbr":"ANO 2011","percent":0.17424242424242425,"count":23}]},"1526":{"id":"542253","name":"Prícina","year":2013,"partyResults":[{"abbr":"ANO 2011","percent":0.17699115044247787,"count":20}]},"1527":{"id":"542270","name":"Pšovlky","year":2013,"partyResults":[{"abbr":"ANO 2011","percent":0.1310344827586207,"count":19}]},"1535":{"id":"542369","name":"Senec","year":2013,"partyResults":[{"abbr":"ANO 2011","percent":0.21951219512195122,"count":27}]},"1536":{"id":"542377","name":"Senomaty","year":2013,"partyResults":[{"abbr":"ANO 2011","percent":0.18470149253731344,"count":99}]},"1544":{"id":"542458","name":"Svojetín","year":2013,"partyResults":[{"abbr":"ANO 2011","percent":0.13157894736842105,"count":15}]},"1546":{"id":"542474","name":"Šanov","year":2013,"partyResults":[{"abbr":"ANO 2011","percent":0.21008403361344538,"count":50}]},"1559":{"id":"542601","name":"Zavidov","year":2013,"partyResults":[{"abbr":"ANO 2011","percent":0.21232876712328766,"count":31}]},"2755":{"id":"559482","name":"Tis u Blatna","year":2013,"partyResults":[{"abbr":"ANO 2011","percent":0.3018867924528302,"count":16}]},"2767":{"id":"559695","name":"Žihle","year":2013,"partyResults":[{"abbr":"ANO 2011","percent":0.17784711388455537,"count":114}]},"3108":{"id":"563412","name":"Veliká Ves","year":2013,"partyResults":[{"abbr":"ANO 2011","percent":0.288,"count":36}]},"3282":{"id":"565181","name":"Dekov","year":2013,"partyResults":[{"abbr":"ANO 2011","percent":0.15942028985507245,"count":11}]},"3283":{"id":"565199","name":"Kolešov","year":2013,"partyResults":[{"abbr":"ANO 2011","percent":0.23404255319148937,"count":11}]},"3290":{"id":"565261","name":"Prílepy","year":2013,"partyResults":[{"abbr":"ANO 2011","percent":0.1388888888888889,"count":15}]},"3291":{"id":"565270","name":"Janov","year":2013,"partyResults":[{"abbr":"ANO 2011","percent":0.20833333333333334,"count":15}]},"3296":{"id":"565326","name":"Švihov","year":2013,"partyResults":[{"abbr":"ANO 2011","percent":0.037037037037037035,"count":1}]},"3314":{"id":"565504","name":"Rerichy","year":2013,"partyResults":[{"abbr":"ANO 2011","percent":0.22580645161290322,"count":14}]},"3315":{"id":"565512","name":"Václavy","year":2013,"partyResults":[{"abbr":"ANO 2011","percent":0.025,"count":1}]},"3363":{"id":"566004","name":"Blatno","year":2013,"partyResults":[{"abbr":"ANO 2011","percent":0.18571428571428572,"count":52}]},"3365":{"id":"566021","name":"Blšany","year":2013,"partyResults":[{"abbr":"ANO 2011","percent":0.23210412147505424,"count":107}]},"3374":{"id":"566128","name":"Deštnice","year":2013,"partyResults":[{"abbr":"ANO 2011","percent":0.32142857142857145,"count":27}]},"3377":{"id":"566152","name":"Domoušice","year":2013,"partyResults":[{"abbr":"ANO 2011","percent":0.20344827586206896,"count":59}]},"3380":{"id":"566187","name":"Holedec","year":2013,"partyResults":[{"abbr":"ANO 2011","percent":0.25961538461538464,"count":81}]},"3383":{"id":"566217","name":"Hrivice","year":2013,"partyResults":[{"abbr":"ANO 2011","percent":0.22291021671826625,"count":72}]},"3390":{"id":"566306","name":"Krásný Dvur","year":2013,"partyResults":[{"abbr":"ANO 2011","percent":0.15181518151815182,"count":46}]},"3391":{"id":"566314","name":"Kryry","year":2013,"partyResults":[{"abbr":"ANO 2011","percent":0.19166666666666668,"count":207}]},"3395":{"id":"566357","name":"Libešice","year":2013,"partyResults":[{"abbr":"ANO 2011","percent":0.2953216374269006,"count":101}]},"3398":{"id":"566381","name":"Liborice","year":2013,"partyResults":[{"abbr":"ANO 2011","percent":0.2127659574468085,"count":30}]},"3400":{"id":"566403","name":"Lipno","year":2013,"partyResults":[{"abbr":"ANO 2011","percent":0.27184466019417475,"count":56}]},"3403":{"id":"566438","name":"Lubenec","year":2013,"partyResults":[{"abbr":"ANO 2011","percent":0.16852367688022285,"count":121}]},"3405":{"id":"566454","name":"Mecholupy","year":2013,"partyResults":[{"abbr":"ANO 2011","percent":0.17050691244239632,"count":74}]},"3412":{"id":"566527","name":"Ocihov","year":2013,"partyResults":[{"abbr":"ANO 2011","percent":0.2808988764044944,"count":50}]},"3416":{"id":"566560","name":"Petrohrad","year":2013,"partyResults":[{"abbr":"ANO 2011","percent":0.12367491166077739,"count":35}]},"3417":{"id":"566578","name":"Pnetluky","year":2013,"partyResults":[{"abbr":"ANO 2011","percent":0.2669902912621359,"count":55}]},"3421":{"id":"566616","name":"Podborany","year":2013,"partyResults":[{"abbr":"ANO 2011","percent":0.1475211608222491,"count":366}]},"3437":{"id":"566781","name":"Pastuchovice","year":2013,"partyResults":[{"abbr":"ANO 2011","percent":0.13636363636363635,"count":6}]},"3444":{"id":"566853","name":"Tuchorice","year":2013,"partyResults":[{"abbr":"ANO 2011","percent":0.18478260869565216,"count":51}]},"3452":{"id":"566934","name":"Vroutek","year":2013,"partyResults":[{"abbr":"ANO 2011","percent":0.1925925925925926,"count":156}]},"3457":{"id":"566985","name":"Žatec","year":2013,"partyResults":[{"abbr":"ANO 2011","percent":0.19915254237288135,"count":1598}]},"4490":{"id":"578924","name":"Velecín","year":2013,"partyResults":[{"abbr":"ANO 2011","percent":0.1509433962264151,"count":8}]},"6119":{"id":"598500","name":"Krty","year":2013,"partyResults":[{"abbr":"ANO 2011","percent":0.12903225806451613,"count":8}]},"6120":{"id":"598518","name":"Ždár","year":2013,"partyResults":[{"abbr":"ANO 2011","percent":0.10526315789473684,"count":4}]}}}