{"grid":["!!!!!!!!!!!!!!!!!!!!!!!!!!!!!!!!!!!!!!!!!!!!!!!!!!!!!!!!!!!!!!!!","!!!!!!!!!!!!!!!!!!!!!!!!!!!!!!!!!!!!!!!!!!!!!!!!!!!!!!!!!!!!!!!!","!!!!!!!!!!!!!!!!!!!!!!!!!!!!!!!!!!!!!!!!!!!!!!!!!!!!!!!!!!!!!!!!","!!!!!!!!!!!!!!!!!!!!!!!!!!!!!!!!!!!!!!!!!!!!!!!!!!!!!!!!!!!!!!!!","!!!!!!!!!!!!!!!!!!!!!!!!!!!!!!!!!!!!!!!!!!!!!!!!!!!!!!!!!!!!!!!!","!!!!!!!!!!!!!!!!!!!!!!!!!!!!!!!!!!!!!!!!!!!!!!!!!!!!!!!!!!!!!!!!","!!!!!!!!!!!!!!!!!!!!!!!!!!!!!!!!!!!!!!!!!!!!!!!!!!!!!!!!!!!!!!!!","!!!!!!!!!!!!!!!!!!!!!!!!!!!!!!!!!!!!!!!!!!!!!!!!!!!!!!!!!!!!!!!!","!!!!!!!!!!!!!!!!!!!!!!!!!!!!!!!!!!!!!!!!!!!!!!!!!!!!!!!!!!!!!!!!","!!!!!!!!!!!!!!!!!!!!!!!!!!!!!!!!!!!!!!!!!!!!!!!!!!!!!!!!!!!!!!!!","!!!!!!!!!!!!!!!!!!!!!!!!!!!!!!!!!!!!!!!!!!!!!!!!!!!!!!!!!!!!!!!!","!!!!!!!!!!!!!!!!!!!!!!!!!!!!!!!!!!!!!!!!!!!!!!!!!!!!!!!!!!!!!!!!","!!!!!!!!!!!!!!!!!!!!!!!!!!!!!!!!!!!!!!!!!!!!!!!!!!!!!!!!!!!!!!!!","!!!!!!!!!!!!!!!!!!!!!!!!!!!!!!!!!!!!!!!!!!!!!!!!!!!!!!!!!!!!!!!!","!!!!!!!!!!!!!!!!!!!!!!!!!!!!!!!!!!!!!!!!!!!!!!!!!!!!!!!!!!!!!!!!","!!!!!!!!!!!!!!!!!!!!!!!!!!!!!!!!!!!!!!!!!!!!!!!!!!!!!!!!!!!!!!!!","!!!!!!!!!!!!!!!!!!!!!!!!!!!!!!!!!!!!!!!!!!!!!!!!!!!!!!!!!!!!!!!!","!!!!!!!!!!!!!!!!!!!!!!!!!!!!!!!!!!!!!!!!!!!!!!!!!!!!!!!!!!!!!!!!","!!!!!!!!!!!!!!!!!!!!!!!!!!!!!!!!!!!!!!!!!!!!!!!!!!!!!!!!!!!!!!!!","!!!!!!!!!!!!!!!!!!!!!!!!!!!!!!!!!!!!!!!!!!!!!!!!!!!!!!!!!!!!!!!!","!!!!!!!!!!!!!!!!!!!!!!!!!!!!!!!!!!!!!!!!!!!!!!!!!!!!!!!!!!!!!!!!","!!!!!!!!!!!!!!!!!!!!!!!!!!!!!!!!!!!!!!!!!!!!!!!!!!!!!!!!!!!!!!!!","!!!!!!!!!!!!!!!!!!!!!!!!!!!!!!!!!!!!!!!!!!!!!!!!!!!!!!!!!!!!!!!!","!!!!!!!!!!!!!!!!!!!!!!!!!!!!!!!!!!!!!!!!!!!!!!!!!!!!!!!!!!!!!!!!","!!!!!!!!!!!!!!!!!!!!!!!!!!!!!!!!!!!!!!!!!!!!!!!!!!!!!!!!!!!!!!!!","!!!!!!!!!!!!!!!!!!!!!!!!!!!!!!!!!!!!!!!!!!!!!!!!!!!!!!!!!!!!!!!!","!!!!!!!!!!!!!!!!!!!!!!!!!!!!!!!!!!!!!!!!!!!!!!!!!!!!!!!!!!!!!!!!","!!!!!!!!!!!!!!!!!!!!!!!!!!!!!!!!!!!!!!!!!!!!!!!!!!!!!!!!!!!!!!!!","!!!!!!!!!!!!!!!!!!!!!!!!!!!!!!!!!!!!!!!!!!!!!!!!!!!!!!!!!!!!!!!!","!!!!!!!!!!!!!!!!!!!!!!!!!!!!!!!!!!!!!!!!!!!!!!!!!!!!!!!!!!!!!!!!","!!!!!!!!!!!!!!!!!!!!!!!!!!!!!!!!!!!!!!!!!!!!!!!!!!!!!!!!!!!!!!!!","!!!!!!!!!!!!!!!!!!!!!!!!!!!!!!!!!!!!!!!!!!!!!!!!!!!!!!!!!!!!!!!!","!!!!!!!!!!!!!!!!!!!!!!!!!!!!!!!!!!!!!!!!!!!!!!!!!!!!!!!!!!!!!!!!","!!!!!!!!!!!!!!!!!!!!!!!!!!!!!!!!!!!!!!!!!!!!!!!!!!!!!!!!!!!!!!!!","!!!!!!!!!!!!!!!!!!!!!!!!!!!!!!!!!!!!!!!!!!!!!!!!!!!!!!!!!!!!!!!!","!!!!!!!!!!!!!!!!!!!!!!!!!!!!!!!!!!!!!!!!!!!!!!!!!!!!!!!!!!!!!!!!","!!!!!!!!!!!!!!!!!!!!!!!!!!!!!!!!!!!!!!!!!!!!!!!!!!!!!!!!!!!!!!!!","!!!!!!!!!!!!!!!!!!!!!!!!!!!!!!!!!!!!!!!!!!!!!!!!!!!!!!!!!!!!!!#!","!!!!!!!!!!!!!!!!!!!!!!!!!!!!!!!!!!!!!!!!!!!!!!!!!!!!!!!!!#######","!!!!!!!!!!!!!!!!!!!!!!!!!!!!!!!!!!!!!!!!!!!!!!!!!!!!!!!!########","!!!!!!!!!!!!!!!!!!!!!!!!!!!!!!!!!!!!!!!!!!!!!!!!!!!!!!!#########","!!!!!!!!!!!!!!!!!!!!!!!!!!!!!!!!!!!!!!!!!!!!!!!!!!!!!###########","!!!!!!!!!!!!!!!!!!!!!!!!!!!!!!!!!!!!!!!!!!!!!!!!!!!!!###########","!!!!!!!!!!!!!!!!!!!!!!!!!!!!!!!!!!!!!!!!!!!!!!!!!!!!!###########","!!!!!!!!!!!!!!!!!!!!!!!!!!!!!!!!!!!!!!!!!!!!!!!!!!!!############","!!!!!!!!!!!!!!!!!!!!!!!!!!!!!!!!!$$$$$$$$$$%!!!!################","!!!!!!!!!!!!!!!!!!!!!!!!!!!!!!!$$$$$$$$$$$$%%%%#################","!!!!!!!!!!!!!!!!!!!!!!!!!!!!!!$$$$$$$$$$$$$%%%%%################","!!!!!!!!!!!!!!!!!!!!!!!!!!!$$$$$$$$$$$$$$$$%%%%%%%##############","!!!!!!!!!!!!!!!!!!!!!!!!!!$$$$$$$$$$$$$$$$$%%%%%%%%%%%##########","!!!!!!!!!!!!!!!!!!!!!!!!!!!$$$$$$$$$$$$$$$$$$%%%$%%%%%%#########","!!!!!!!!!!!!!!!!!!!!!!!!!!!$$$$$$$$$$$$$$$$$$$$$$$%%%%%%%%######","!!!!!!!!!!!!!!!!!!!!!!!!!!!!$$$$$$$$$$$$$$$$$$$$$$%%%%%%%%%#####","!!!!!!!!!!!!!!!!!!!!!!!!!!!!!$$$$$$$$$$$$$$$$$$$$%%%%%%%%%%#####","!!!!!!!!!!!!!!!!!!!!!!!!!!!!!!$$$$$$$$$$$$$$$$$$$%%%%%%%%%%#####","!!!!!!!!!!!!!!!!!!!!!!!!!!!!!!$$$$$$$$$$$$$$$$$$$$$$%%%%%%%#####","!!!!!!!!!!!!!!!!!!!!!!!!!!!!!!$$$$$$$$$$$$$$$$$$$$$$%%%%%%%%####","!!!!!!!!!!!!!!!!!!!!!!!!!!!!!!!$$$$$$$$$$$$$$$$$$$$$$$%%%%%%####","!!!!!!!!!!!!!!!!!!!!!!!!!!!!!!!$$$$$$$$$$$$$$$$$$$$$$$%%%%%%####","!!!!!!!!!!!!!!!!!!!!!!!!!!!!!!!$$$$$$$$$$$$$$$$$$$$$$%%%%%%%####","!!!!!!!!!!!!!!!!!!!!!!!!!!!!!!!$$$$$$$$$$$$$$$$$$$$$%%%%%%%%%%##","!!!!!!!!!!!!!!!!!!!!!!!!!!!!!!$$$$$$$$$$$$$$$$$$$$$$$%%%%%%%%%%%","!!!!!!!!!!!!!!!!!!!!!!!!!!!!!!$$$$$$$$$$$$$$$$$$$$$$$$$%%%%%%%%%","!!!!!!!!!!!!!!!!!!!!!!!!!!!!!!!$&$$$$$$$$$$$$$$$$$$$$%%%%%%%%%%%"],"keys":["0",0,"3508","3467","3511","3471"],"data":{"0":null,"3467":{"id":"567108","name":"Ceský Jiretín","year":2002,"partyResults":[{"abbr":"ČSNS","percent":0,"count":0},{"abbr":"SZR","percent":0,"count":0},{"abbr":"BPS","percent":0,"count":null},{"abbr":"ČP","percent":0,"count":0},{"abbr":"SNK ED","percent":0,"count":0},{"abbr":"PB","percent":0,"count":0},{"abbr":"SZ","percent":0.0625,"count":3},{"abbr":"NDS","percent":0,"count":0},{"abbr":"DL","percent":0,"count":0},{"abbr":"VPB","percent":0,"count":0},{"abbr":"HA","percent":0,"count":0},{"abbr":"AZSD","percent":0,"count":null},{"abbr":"N","percent":0,"count":0},{"abbr":"NH","percent":0,"count":null},{"abbr":"RMS","percent":0.041666666666666664,"count":2},{"abbr":"CZ","percent":0,"count":0},{"abbr":"ROI","percent":0,"count":null},{"abbr":"SV SOS","percent":0,"count":0},{"abbr":"ČSDH","percent":0,"count":0},{"abbr":"REP","percent":0,"count":0},{"abbr":"ODA","percent":0,"count":0},{"abbr":"MoDS","percent":0,"count":null},{"abbr":"DŽJ","percent":0,"count":null}]},"3471":{"id":"567191","name":"Klíny","year":2002,"partyResults":[{"abbr":"ČSNS","percent":0,"count":0},{"abbr":"SZR","percent":0.023809523809523808,"count":1},{"abbr":"BPS","percent":0,"count":null},{"abbr":"ČP","percent":0,"count":0},{"abbr":"SNK ED","percent":0,"count":0},{"abbr":"PB","percent":0.023809523809523808,"count":1},{"abbr":"SZ","percent":0.07142857142857142,"count":3},{"abbr":"NDS","percent":0,"count":0},{"abbr":"DL","percent":0,"count":0},{"abbr":"VPB","percent":0,"count":0},{"abbr":"HA","percent":0,"count":0},{"abbr":"AZSD","percent":0,"count":null},{"abbr":"N","percent":0,"count":0},{"abbr":"NH","percent":0,"count":null},{"abbr":"RMS","percent":0,"count":0},{"abbr":"CZ","percent":0,"count":0},{"abbr":"ROI","percent":0,"count":null},{"abbr":"SV SOS","percent":0,"count":0},{"abbr":"ČSDH","percent":0,"count":0},{"abbr":"REP","percent":0,"count":0},{"abbr":"ODA","percent":0,"count":0},{"abbr":"MoDS","percent":0,"count":null},{"abbr":"DŽJ","percent":0,"count":null}]},"3508":{"id":"567728","name":"Moldava","year":2002,"partyResults":[{"abbr":"ČSNS","percent":0,"count":0},{"abbr":"SZR","percent":0,"count":0},{"abbr":"BPS","percent":0,"count":null},{"abbr":"ČP","percent":0,"count":0},{"abbr":"SNK ED","percent":0.06060606060606061,"count":4},{"abbr":"PB","percent":0,"count":0},{"abbr":"SZ","percent":0,"count":0},{"abbr":"NDS","percent":0,"count":0},{"abbr":"DL","percent":0,"count":0},{"abbr":"VPB","percent":0,"count":0},{"abbr":"HA","percent":0,"count":0},{"abbr":"AZSD","percent":0,"count":null},{"abbr":"N","percent":0,"count":0},{"abbr":"NH","percent":0,"count":null},{"abbr":"RMS","percent":0,"count":0},{"abbr":"CZ","percent":0,"count":0},{"abbr":"ROI","percent":0,"count":null},{"abbr":"SV SOS","percent":0.015151515151515152,"count":1},{"abbr":"ČSDH","percent":0.015151515151515152,"count":1},{"abbr":"REP","percent":0,"count":0},{"abbr":"ODA","percent":0.015151515151515152,"count":1},{"abbr":"MoDS","percent":0,"count":null},{"abbr":"DŽJ","percent":0,"count":null}]},"3511":{"id":"567779","name":"Osek","year":2002,"partyResults":[{"abbr":"ČSNS","percent":0.0029985007496251873,"count":6},{"abbr":"SZR","percent":0.0014992503748125937,"count":3},{"abbr":"BPS","percent":0,"count":null},{"abbr":"ČP","percent":0.0004997501249375312,"count":1},{"abbr":"SNK ED","percent":0.0239880059970015,"count":48},{"abbr":"PB","percent":0.015992003998001,"count":32},{"abbr":"SZ","percent":0.015992003998001,"count":32},{"abbr":"NDS","percent":0.0009995002498750624,"count":2},{"abbr":"DL","percent":0.001999000499750125,"count":4},{"abbr":"VPB","percent":0.0029985007496251873,"count":6},{"abbr":"HA","percent":0.0004997501249375312,"count":1},{"abbr":"AZSD","percent":0,"count":null},{"abbr":"N","percent":0.0069965017491254375,"count":14},{"abbr":"NH","percent":0,"count":null},{"abbr":"RMS","percent":0.025487256371814093,"count":51},{"abbr":"CZ","percent":0,"count":0},{"abbr":"ROI","percent":0,"count":null},{"abbr":"SV SOS","percent":0.0074962518740629685,"count":15},{"abbr":"ČSDH","percent":0.0014992503748125937,"count":3},{"abbr":"REP","percent":0.0024987506246876563,"count":5},{"abbr":"ODA","percent":0.008995502248875561,"count":18},{"abbr":"MoDS","percent":0,"count":null},{"abbr":"DŽJ","percent":0,"count":null}]}}}